{
  "Pitcher": {
    "Central": {
      "防御率": "3.90",
      "登板": "1769",
      "先発": "422",
      "完投": "21",
      "完封": "8",
      "QS": "198",
      "勝利": "194",
      "敗戦": "194",
      "ホールド": "298",
      "HP": "349",
      "セーブ": "85",
      "勝率": "0.500",
      "投球回": "3685.5",
      "被安打": "3588",
      "被本塁打": "399",
      "奪三振": "3198",
      "奪三振率": "7.81",
      "与四球": "1344",
      "与死球": "121",
      "暴投": "124",
      "ボーク": "9",
      "失点": "1759",
      "自責点": "1598",
      "被打率": "0.251",
      "K/BB": "2.38",
      "WHIP": "1.34",
      "アウト": "11151.0",
      "故意四球": "90",
      "打者": "15750",
      "被打数": "14285",
      "QS率": "46.9",
      "BABIP": ".298",
      "BB/9": "3.28",
      "HR/9": "0.97",
      "K%": "20.3",
      "BB%": "8.5",
      "HR%": "2.53",
      "K-BB%": "11.8",
      "LOB%": "73.3",
      "小松式ドネーション": "16921000",
      "ONE OUTS(万)": "-3219500"
    },
    "Pacific": {
      "防御率": "4.05",
      "登板": "1821",
      "先発": "418",
      "完投": "7",
      "完封": "4",
      "QS": "178",
      "勝利": "200",
      "敗戦": "199",
      "ホールド": "338",
      "HP": "402",
      "セーブ": "104",
      "勝率": "0.501",
      "投球回": "3669.6",
      "被安打": "3405",
      "被本塁打": "388",
      "奪三振": "3128",
      "奪三振率": "7.67",
      "与四球": "1562",
      "与死球": "165",
      "暴投": "96",
      "ボーク": "5",
      "失点": "1792",
      "自責点": "1650",
      "被打率": "0.241",
      "K/BB": "2.00",
      "WHIP": "1.35",
      "アウト": "11111.0",
      "故意四球": "43",
      "打者": "15867",
      "被打数": "14140",
      "QS率": "42.6",
      "BABIP": ".284",
      "BB/9": "3.83",
      "HR/9": "0.95",
      "K%": "19.7",
      "BB%": "9.8",
      "HR%": "2.45",
      "K-BB%": "9.9",
      "LOB%": "72.8",
      "小松式ドネーション": "17531000",
      "ONE OUTS(万)": "-3404500"
    }
  },
  "Hitter": {
    "Central": {
      "打率": "0.264",
      "試合": "5133",
      "打席": "14775",
      "打数": "13102",
      "安打": "3454",
      "二塁打": "623",
      "三塁打": "45",
      "本塁打": "385",
      "塁打": "5322",
      "打点": "1610",
      "得点": "1707",
      "三振": "2758",
      "四球": "1309",
      "死球": "120",
      "犠打": "161",
      "犠飛": "83",
      "盗塁": "188",
      "盗塁死": "106",
      "併殺打": "308",
      "出塁率": "0.334",
      "長打率": "0.406",
      "OPS": "0.740",
      "失策": "171",
      "故意四球": "82",
      "本塁打率": ".0294",
      "盗成功率": "63.9",
      "wOBA": ".325",
      "RC": "1771.91",
      "RC27": "4.64",
      "XR": "1761.47",
      "XR27": "4.61",
      "IsoP": ".143",
      "BB/K": "0.47",
      "BB%": "8.9",
      "K%": "18.7",
      "IsoD": ".070",
      "BABIP": ".306",
      "アダムダン率": "30.1",
      "ONE OUTS(万)": "-8720000"
    },
    "Pacific": {
      "打率": "0.248",
      "試合": "5020",
      "打席": "15904",
      "打数": "13803",
      "安打": "3418",
      "二塁打": "595",
      "三塁打": "78",
      "本塁打": "385",
      "塁打": "5324",
      "打点": "1736",
      "得点": "1815",
      "三振": "3124",
      "四球": "1572",
      "死球": "163",
      "犠打": "261",
      "犠飛": "104",
      "盗塁": "285",
      "盗塁死": "119",
      "併殺打": "261",
      "出塁率": "0.329",
      "長打率": "0.386",
      "OPS": "0.715",
      "失策": "187",
      "故意四球": "45",
      "本塁打率": ".0279",
      "盗成功率": "70.5",
      "wOBA": ".317",
      "RC": "1817.96",
      "RC27": "4.41",
      "XR": "1835.70",
      "XR27": "4.45",
      "IsoP": ".138",
      "BB/K": "0.50",
      "BB%": "9.9",
      "K%": "19.6",
      "IsoD": ".081",
      "BABIP": ".292",
      "アダムダン率": "31.9",
      "ONE OUTS(万)": "-9260000"
    }
  }
}