{
  "Team": [
    {
      "チーム": "巨人",
      "League": "Central",
      "試合": "57",
      "勝利": "33",
      "敗戦": "21",
      "引分": "3",
      "勝率": ".611",
      "勝差": "0",
      "残試合": "63",
      "得点": "268",
      "失点": "196",
      "本塁打": "77",
      "盗塁": "37",
      "打率": ".257",
      "防御率": "3.42",
      "登板": "255",
      "先発": "56",
      "完投": "3",
      "完封": "3",
      "QS": "25",
      "ホールド": "40",
      "HP": "47",
      "セーブ": "12",
      "投球回": "497.0",
      "被安打": "415",
      "被本塁打": "53",
      "奪三振": "418",
      "奪三振率": "7.57",
      "与四球": "185",
      "与死球": "21",
      "暴投": "7",
      "ボーク": "0",
      "自責点": "188",
      "被打率": "0.227",
      "K/BB": "2.26",
      "WHIP": "1.21",
      "アウト": "1505.0",
      "故意四球": "9",
      "打者": "2035",
      "被打数": "1829",
      "打席": "2035",
      "打数": "1804",
      "安打": "481",
      "二塁打": "85",
      "三塁打": "6",
      "塁打": "809",
      "打点": "252",
      "三振": "428",
      "四球": "199",
      "死球": "10",
      "犠打": "13",
      "犠飛": "9",
      "盗塁死": "14",
      "併殺打": "37",
      "出塁率": "0.341",
      "長打率": "0.448",
      "OPS": "0.790",
      "失策": "13"
    },
    {
      "チーム": "ＤｅＮＡ",
      "League": "Central",
      "試合": "60",
      "勝利": "30",
      "敗戦": "27",
      "引分": "3",
      "勝率": ".526",
      "勝差": "4.5",
      "残試合": "60",
      "得点": "241",
      "失点": "222",
      "本塁打": "60",
      "盗塁": "13",
      "打率": ".268",
      "防御率": "3.55",
      "登板": "261",
      "先発": "60",
      "完投": "1",
      "完封": "0",
      "QS": "28",
      "ホールド": "51",
      "HP": "57",
      "セーブ": "14",
      "投球回": "518.5",
      "被安打": "480",
      "被本塁打": "46",
      "奪三振": "470",
      "奪三振率": "8.14",
      "与四球": "187",
      "与死球": "21",
      "暴投": "16",
      "ボーク": "1",
      "自責点": "206",
      "被打率": "0.246",
      "K/BB": "2.51",
      "WHIP": "1.28",
      "アウト": "1566.0",
      "故意四球": "20",
      "打者": "2163",
      "被打数": "1955",
      "打席": "1880",
      "打数": "1690",
      "安打": "472",
      "二塁打": "79",
      "三塁打": "2",
      "塁打": "708",
      "打点": "199",
      "三振": "315",
      "四球": "152",
      "死球": "16",
      "犠打": "12",
      "犠飛": "10",
      "盗塁死": "8",
      "併殺打": "44",
      "出塁率": "0.343",
      "長打率": "0.419",
      "OPS": "0.762",
      "失策": "18"
    },
    {
      "チーム": "阪神",
      "League": "Central",
      "試合": "58",
      "勝利": "27",
      "敗戦": "28",
      "引分": "3",
      "勝率": ".491",
      "勝差": "2",
      "残試合": "62",
      "得点": "247",
      "失点": "230",
      "本塁打": "55",
      "盗塁": "40",
      "打率": ".243",
      "防御率": "3.59",
      "登板": "205",
      "先発": "58",
      "完投": "3",
      "完封": "0",
      "QS": "35",
      "ホールド": "30",
      "HP": "35",
      "セーブ": "12",
      "投球回": "486.7",
      "被安打": "450",
      "被本塁打": "50",
      "奪三振": "400",
      "奪三振率": "7.37",
      "与四球": "176",
      "与死球": "14",
      "暴投": "23",
      "ボーク": "2",
      "自責点": "197",
      "被打率": "0.238",
      "K/BB": "2.27",
      "WHIP": "1.28",
      "アウト": "1472.0",
      "故意四球": "13",
      "打者": "2080",
      "被打数": "1890",
      "打席": "2027",
      "打数": "1770",
      "安打": "444",
      "二塁打": "74",
      "三塁打": "8",
      "塁打": "696",
      "打点": "233",
      "三振": "391",
      "四球": "201",
      "死球": "18",
      "犠打": "25",
      "犠飛": "13",
      "盗塁死": "18",
      "併殺打": "41",
      "出塁率": "0.331",
      "長打率": "0.393",
      "OPS": "0.724",
      "失策": "30"
    },
    {
      "チーム": "中日",
      "League": "Central",
      "試合": "61",
      "勝利": "27",
      "敗戦": "30",
      "引分": "4",
      "勝率": ".474",
      "勝差": "1",
      "残試合": "59",
      "得点": "204",
      "失点": "248",
      "本塁打": "33",
      "盗塁": "15",
      "打率": ".240",
      "防御率": "3.75",
      "登板": "249",
      "先発": "61",
      "完投": "5",
      "完封": "1",
      "QS": "28",
      "ホールド": "39",
      "HP": "46",
      "セーブ": "12",
      "投球回": "531.4",
      "被安打": "501",
      "被本塁打": "59",
      "奪三振": "481",
      "奪三振率": "8.13",
      "与四球": "188",
      "与死球": "20",
      "暴投": "17",
      "ボーク": "0",
      "自責点": "224",
      "被打率": "0.249",
      "K/BB": "2.56",
      "WHIP": "1.29",
      "アウト": "1611.0",
      "故意四球": "7",
      "打者": "2220",
      "被打数": "2012",
      "打席": "2139",
      "打数": "1902",
      "安打": "472",
      "二塁打": "87",
      "三塁打": "8",
      "塁打": "674",
      "打点": "193",
      "三振": "376",
      "四球": "178",
      "死球": "16",
      "犠打": "27",
      "犠飛": "16",
      "盗塁死": "9",
      "併殺打": "45",
      "出塁率": "0.315",
      "長打率": "0.354",
      "OPS": "0.670",
      "失策": "24"
    },
    {
      "チーム": "広島",
      "League": "Central",
      "試合": "58",
      "勝利": "24",
      "敗戦": "28",
      "引分": "6",
      "勝率": ".462",
      "勝差": "0.5",
      "残試合": "62",
      "得点": "251",
      "失点": "262",
      "本塁打": "62",
      "盗塁": "24",
      "打率": ".267",
      "防御率": "4.12",
      "登板": "239",
      "先発": "58",
      "完投": "4",
      "完封": "1",
      "QS": "29",
      "ホールド": "27",
      "HP": "33",
      "セーブ": "9",
      "投球回": "509.9",
      "被安打": "518",
      "被本塁打": "51",
      "奪三振": "450",
      "奪三振率": "7.91",
      "与四球": "205",
      "与死球": "11",
      "暴投": "23",
      "ボーク": "0",
      "自責点": "234",
      "被打率": "0.261",
      "K/BB": "2.20",
      "WHIP": "1.41",
      "アウト": "1543.0",
      "故意四球": "12",
      "打者": "2200",
      "被打数": "1984",
      "打席": "2055",
      "打数": "1821",
      "安打": "503",
      "二塁打": "97",
      "三塁打": "7",
      "塁打": "791",
      "打点": "231",
      "三振": "377",
      "四球": "177",
      "死球": "18",
      "犠打": "35",
      "犠飛": "4",
      "盗塁死": "16",
      "併殺打": "41",
      "出塁率": "0.346",
      "長打率": "0.434",
      "OPS": "0.780",
      "失策": "30"
    },
    {
      "チーム": "ヤクルト",
      "League": "Central",
      "試合": "58",
      "勝利": "23",
      "敗戦": "30",
      "引分": "5",
      "勝率": ".434",
      "勝差": "1.5",
      "残試合": "62",
      "得点": "251",
      "失点": "304",
      "本塁打": "52",
      "盗塁": "36",
      "打率": ".248",
      "防御率": "4.85",
      "登板": "264",
      "先発": "58",
      "完投": "1",
      "完封": "1",
      "QS": "21",
      "ホールド": "54",
      "HP": "62",
      "セーブ": "9",
      "投球回": "514.3",
      "被安打": "590",
      "被本塁打": "78",
      "奪三振": "430",
      "奪三振率": "7.51",
      "与四球": "202",
      "与死球": "14",
      "暴投": "12",
      "ボーク": "3",
      "自責点": "280",
      "被打率": "0.282",
      "K/BB": "2.13",
      "WHIP": "1.54",
      "アウト": "1559.0",
      "故意四球": "12",
      "打者": "2311",
      "被打数": "2095",
      "打席": "2101",
      "打数": "1833",
      "安打": "464",
      "二塁打": "94",
      "三塁打": "5",
      "塁打": "724",
      "打点": "233",
      "三振": "397",
      "四球": "208",
      "死球": "21",
      "犠打": "27",
      "犠飛": "12",
      "盗塁死": "25",
      "併殺打": "40",
      "出塁率": "0.334",
      "長打率": "0.395",
      "OPS": "0.729",
      "失策": "27"
    },
    {
      "チーム": "ソフトバンク",
      "League": "Pacific",
      "試合": "60",
      "勝利": "35",
      "敗戦": "23",
      "引分": "2",
      "勝率": ".603",
      "勝差": "0",
      "残試合": "60",
      "得点": "263",
      "失点": "217",
      "本塁打": "72",
      "盗塁": "40",
      "打率": ".242",
      "防御率": "3.35",
      "登板": "252",
      "先発": "54",
      "完投": "1",
      "完封": "1",
      "QS": "26",
      "ホールド": "70",
      "HP": "80",
      "セーブ": "16",
      "投球回": "499.0",
      "被安打": "409",
      "被本塁打": "43",
      "奪三振": "484",
      "奪三振率": "8.73",
      "与四球": "230",
      "与死球": "29",
      "暴投": "11",
      "ボーク": "1",
      "自責点": "188",
      "被打率": "0.224",
      "K/BB": "2.10",
      "WHIP": "1.28",
      "アウト": "1511.0",
      "故意四球": "4",
      "打者": "2088",
      "被打数": "1829",
      "打席": "2142",
      "打数": "1875",
      "安打": "455",
      "二塁打": "76",
      "三塁打": "15",
      "塁打": "771",
      "打点": "247",
      "三振": "408",
      "四球": "199",
      "死球": "12",
      "犠打": "35",
      "犠飛": "21",
      "盗塁死": "14",
      "併殺打": "19",
      "出塁率": "0.316",
      "長打率": "0.411",
      "OPS": "0.727",
      "失策": "18"
    },
    {
      "チーム": "ロッテ",
      "League": "Pacific",
      "試合": "60",
      "勝利": "33",
      "敗戦": "25",
      "引分": "2",
      "勝率": ".569",
      "勝差": "2",
      "残試合": "60",
      "得点": "263",
      "失点": "276",
      "本塁打": "54",
      "盗塁": "48",
      "打率": ".244",
      "防御率": "4.43",
      "登板": "228",
      "先発": "59",
      "完投": "1",
      "完封": "1",
      "QS": "28",
      "ホールド": "42",
      "HP": "50",
      "セーブ": "18",
      "投球回": "508.8",
      "被安打": "509",
      "被本塁打": "61",
      "奪三振": "415",
      "奪三振率": "7.31",
      "与四球": "198",
      "与死球": "16",
      "暴投": "11",
      "ボーク": "2",
      "自責点": "240",
      "被打率": "0.261",
      "K/BB": "2.10",
      "WHIP": "1.38",
      "アウト": "1539.0",
      "故意四球": "7",
      "打者": "2165",
      "被打数": "1951",
      "打席": "2225",
      "打数": "1868",
      "安打": "461",
      "二塁打": "83",
      "三塁打": "4",
      "塁打": "714",
      "打点": "247",
      "三振": "435",
      "四球": "270",
      "死球": "36",
      "犠打": "38",
      "犠飛": "13",
      "盗塁死": "18",
      "併殺打": "41",
      "出塁率": "0.351",
      "長打率": "0.382",
      "OPS": "0.733",
      "失策": "20"
    },
    {
      "チーム": "楽天",
      "League": "Pacific",
      "試合": "60",
      "勝利": "31",
      "敗戦": "26",
      "引分": "3",
      "勝率": ".544",
      "勝差": "1.5",
      "残試合": "60",
      "得点": "318",
      "失点": "265",
      "本塁打": "62",
      "盗塁": "42",
      "打率": ".272",
      "防御率": "4.19",
      "登板": "261",
      "先発": "60",
      "完投": "1",
      "完封": "1",
      "QS": "27",
      "ホールド": "42",
      "HP": "50",
      "セーブ": "14",
      "投球回": "520.5",
      "被安打": "487",
      "被本塁打": "61",
      "奪三振": "440",
      "奪三振率": "7.59",
      "与四球": "198",
      "与死球": "24",
      "暴投": "11",
      "ボーク": "1",
      "自責点": "243",
      "被打率": "0.243",
      "K/BB": "2.22",
      "WHIP": "1.31",
      "アウト": "1579.0",
      "故意四球": "8",
      "打者": "2225",
      "被打数": "2003",
      "打席": "2339",
      "打数": "2024",
      "安打": "551",
      "二塁打": "114",
      "三塁打": "12",
      "塁打": "875",
      "打点": "307",
      "三振": "443",
      "四球": "239",
      "死球": "26",
      "犠打": "33",
      "犠飛": "17",
      "盗塁死": "14",
      "併殺打": "41",
      "出塁率": "0.354",
      "長打率": "0.432",
      "OPS": "0.786",
      "失策": "26"
    },
    {
      "チーム": "日本ハム",
      "League": "Pacific",
      "試合": "60",
      "勝利": "29",
      "敗戦": "28",
      "引分": "3",
      "勝率": ".509",
      "勝差": "2",
      "残試合": "60",
      "得点": "265",
      "失点": "269",
      "本塁打": "53",
      "盗塁": "31",
      "打率": ".250",
      "防御率": "4.06",
      "登板": "260",
      "先発": "59",
      "完投": "1",
      "完封": "0",
      "QS": "26",
      "ホールド": "50",
      "HP": "59",
      "セーブ": "14",
      "投球回": "521.7",
      "被安打": "499",
      "被本塁打": "51",
      "奪三振": "469",
      "奪三振率": "8.07",
      "与四球": "212",
      "与死球": "24",
      "暴投": "16",
      "ボーク": "0",
      "自責点": "233",
      "被打率": "0.242",
      "K/BB": "2.21",
      "WHIP": "1.36",
      "アウト": "1577.0",
      "故意四球": "9",
      "打者": "2302",
      "被打数": "2066",
      "打席": "2248",
      "打数": "1954",
      "安打": "488",
      "二塁打": "77",
      "三塁打": "7",
      "塁打": "738",
      "打点": "254",
      "三振": "429",
      "四球": "223",
      "死球": "19",
      "犠打": "37",
      "犠飛": "15",
      "盗塁死": "9",
      "併殺打": "44",
      "出塁率": "0.330",
      "長打率": "0.378",
      "OPS": "0.708",
      "失策": "34"
    },
    {
      "チーム": "西武",
      "League": "Pacific",
      "試合": "58",
      "勝利": "24",
      "敗戦": "32",
      "引分": "2",
      "勝率": ".429",
      "勝差": "4.5",
      "残試合": "62",
      "得点": "253",
      "失点": "273",
      "本塁打": "58",
      "盗塁": "39",
      "打率": ".249",
      "防御率": "4.57",
      "登板": "263",
      "先発": "58",
      "完投": "0",
      "完封": "0",
      "QS": "19",
      "ホールド": "38",
      "HP": "50",
      "セーブ": "12",
      "投球回": "501.1",
      "被安打": "502",
      "被本塁打": "59",
      "奪三振": "365",
      "奪三振率": "6.55",
      "与四球": "223",
      "与死球": "27",
      "暴投": "13",
      "ボーク": "1",
      "自責点": "257",
      "被打率": "0.259",
      "K/BB": "1.64",
      "WHIP": "1.45",
      "アウト": "1518.0",
      "故意四球": "2",
      "打者": "2188",
      "被打数": "1938",
      "打席": "2150",
      "打数": "1890",
      "安打": "471",
      "二塁打": "83",
      "三塁打": "15",
      "塁打": "740",
      "打点": "235",
      "三振": "469",
      "四球": "200",
      "死球": "28",
      "犠打": "21",
      "犠飛": "11",
      "盗塁死": "21",
      "併殺打": "33",
      "出塁率": "0.328",
      "長打率": "0.392",
      "OPS": "0.720",
      "失策": "23"
    },
    {
      "チーム": "オリックス",
      "League": "Pacific",
      "試合": "60",
      "勝利": "19",
      "敗戦": "37",
      "引分": "4",
      "勝率": ".339",
      "勝差": "5",
      "残試合": "60",
      "得点": "209",
      "失点": "271",
      "本塁打": "41",
      "盗塁": "41",
      "打率": ".242",
      "防御率": "4.31",
      "登板": "262",
      "先発": "58",
      "完投": "1",
      "完封": "0",
      "QS": "22",
      "ホールド": "39",
      "HP": "47",
      "セーブ": "9",
      "投球回": "501.6",
      "被安打": "464",
      "被本塁打": "58",
      "奪三振": "418",
      "奪三振率": "7.48",
      "与四球": "244",
      "与死球": "20",
      "暴投": "12",
      "ボーク": "0",
      "自責点": "245",
      "被打率": "0.244",
      "K/BB": "1.71",
      "WHIP": "1.41",
      "アウト": "1523.0",
      "故意四球": "8",
      "打者": "2164",
      "被打数": "1900",
      "打席": "2213",
      "打数": "1949",
      "安打": "474",
      "二塁打": "82",
      "三塁打": "7",
      "塁打": "693",
      "打点": "201",
      "三振": "419",
      "四球": "188",
      "死球": "19",
      "犠打": "48",
      "犠飛": "9",
      "盗塁死": "24",
      "併殺打": "40",
      "出塁率": "0.315",
      "長打率": "0.356",
      "OPS": "0.670",
      "失策": "31"
    }
  ]
}