{
  "Pitcher": {
    "Central": {
      "防御率": "3.92",
      "登板": "3636",
      "先発": "846",
      "完投": "30",
      "完封": "17",
      "無四球": "8",
      "QS": "376",
      "交代完了": "814",
      "勝利": "408",
      "敗戦": "419",
      "ホールド": "685",
      "HP": "823",
      "セーブ": "186",
      "勝率": "0.493",
      "投球回": "7506.0",
      "打者": "32376",
      "被安打": "7253",
      "被本塁打": "841",
      "奪三振": "6551",
      "奪三振率": "7.85",
      "与四球": "2803",
      "与死球": "287",
      "暴投": "210",
      "ボーク": "11",
      "失点": "3589",
      "自責点": "3273",
      "被打率": "0.254",
      "K/BB": "2.34",
      "WHIP": "1.34",
      "アウト": "22644.0",
      "対右": {
        "被打率": "0.252",
        "被打数": "15447",
        "被安打": "3893",
        "被本塁打": "567",
        "奪三振": "3659",
        "与四球": "1572",
        "与死球": "176"
      },
      "対左": {
        "被打率": "0.256",
        "被打数": "13102",
        "被安打": "3360",
        "被本塁打": "274",
        "奪三振": "2892",
        "与四球": "1231",
        "与死球": "111"
      },
      "被打数": "28549",
      "球場": {
        "東京ドーム": {
          "防御率": "4.54",
          "登板": "524",
          "完投": "2",
          "完封": "1",
          "無四球": "1",
          "勝利": "59",
          "敗戦": "57",
          "ホールド": "83",
          "HP": "103",
          "セーブ": "29",
          "勝率": "0.509",
          "投球回": "1016.6",
          "打者": "4505",
          "被安打": "1021",
          "被本塁打": "164",
          "奪三振": "941",
          "奪三振率": "8.32",
          "与四球": "417",
          "与死球": "49",
          "暴投": "20",
          "ボーク": "3",
          "失点": "547",
          "自責点": "513"
        },
        "神宮": {
          "防御率": "4.91",
          "登板": "556",
          "完投": "2",
          "完封": "1",
          "無四球": "0",
          "勝利": "58",
          "敗戦": "61",
          "ホールド": "105",
          "HP": "124",
          "セーブ": "27",
          "勝率": "0.487",
          "投球回": "1079.7",
          "打者": "4817",
          "被安打": "1124",
          "被本塁打": "181",
          "奪三振": "1012",
          "奪三振率": "8.42",
          "与四球": "420",
          "与死球": "38",
          "暴投": "43",
          "ボーク": "0",
          "失点": "636",
          "自責点": "590"
        },
        "横浜": {
          "防御率": "4.06",
          "登板": "573",
          "完投": "7",
          "完封": "4",
          "無四球": "0",
          "勝利": "66",
          "敗戦": "63",
          "ホールド": "101",
          "HP": "124",
          "セーブ": "27",
          "勝率": "0.512",
          "投球回": "1150.3",
          "打者": "5011",
          "被安打": "1113",
          "被本塁打": "149",
          "奪三振": "1019",
          "奪三振率": "7.97",
          "与四球": "447",
          "与死球": "33",
          "暴投": "32",
          "ボーク": "2",
          "失点": "561",
          "自責点": "519"
        },
        "ナゴヤドーム": {
          "防御率": "3.44",
          "登板": "547",
          "完投": "5",
          "完封": "3",
          "無四球": "2",
          "勝利": "64",
          "敗戦": "65",
          "ホールド": "113",
          "HP": "131",
          "セーブ": "32",
          "勝率": "0.496",
          "投球回": "1165.9",
          "打者": "4936",
          "被安打": "1064",
          "被本塁打": "73",
          "奪三振": "1023",
          "奪三振率": "7.88",
          "与四球": "352",
          "与死球": "48",
          "暴投": "33",
          "ボーク": "1",
          "失点": "473",
          "自責点": "447"
        },
        "甲子園": {
          "防御率": "3.24",
          "登板": "453",
          "完投": "4",
          "完封": "3",
          "無四球": "1",
          "勝利": "54",
          "敗戦": "56",
          "ホールド": "84",
          "HP": "105",
          "セーブ": "27",
          "勝率": "0.491",
          "投球回": "979.2",
          "打者": "4219",
          "被安打": "956",
          "被本塁打": "74",
          "奪三振": "799",
          "奪三振率": "7.34",
          "与四球": "351",
          "与死球": "37",
          "暴投": "23",
          "ボーク": "2",
          "失点": "406",
          "自責点": "353"
        },
        "京セラＤ大阪": {
          "防御率": "3.73",
          "登板": "138",
          "完投": "0",
          "完封": "0",
          "無四球": "0",
          "勝利": "14",
          "敗戦": "16",
          "ホールド": "38",
          "HP": "43",
          "セーブ": "6",
          "勝率": "0.467",
          "投球回": "264.4",
          "打者": "1172",
          "被安打": "252",
          "被本塁打": "14",
          "奪三振": "245",
          "奪三振率": "8.31",
          "与四球": "106",
          "与死球": "8",
          "暴投": "9",
          "ボーク": "2",
          "失点": "122",
          "自責点": "110"
        },
        "鹿児島": {
          "防御率": "5.29",
          "登板": "8",
          "完投": "0",
          "完封": "0",
          "無四球": "0",
          "勝利": "1",
          "敗戦": "1",
          "ホールド": "0",
          "HP": "0",
          "セーブ": "0",
          "勝率": "0.500",
          "投球回": "17",
          "打者": "74",
          "被安打": "13",
          "被本塁打": "3",
          "奪三振": "20",
          "奪三振率": "10.59",
          "与四球": "9",
          "与死球": "1",
          "暴投": "2",
          "ボーク": "0",
          "失点": "10",
          "自責点": "10"
        },
        "札幌ドーム": {
          "防御率": "3.24",
          "登板": "36",
          "完投": "1",
          "完封": "0",
          "無四球": "0",
          "勝利": "3",
          "敗戦": "5",
          "ホールド": "9",
          "HP": "9",
          "セーブ": "0",
          "勝率": "0.375",
          "投球回": "78.8",
          "打者": "343",
          "被安打": "70",
          "被本塁打": "5",
          "奪三振": "72",
          "奪三振率": "8.03",
          "与四球": "27",
          "与死球": "3",
          "暴投": "2",
          "ボーク": "0",
          "失点": "32",
          "自責点": "29"
        },
        "秋田": {
          "防御率": "2.75",
          "登板": "18",
          "完投": "0",
          "完封": "0",
          "無四球": "0",
          "勝利": "2",
          "敗戦": "2",
          "ホールド": "3",
          "HP": "4",
          "セーブ": "1",
          "勝率": "0.500",
          "投球回": "34.6",
          "打者": "162",
          "被安打": "39",
          "被本塁打": "3",
          "奪三振": "28",
          "奪三振率": "7.00",
          "与四球": "14",
          "与死球": "3",
          "暴投": "2",
          "ボーク": "0",
          "失点": "15",
          "自責点": "11"
        },
        "マツダスタジアム": {
          "防御率": "3.65",
          "登板": "549",
          "完投": "6",
          "完封": "4",
          "無四球": "3",
          "勝利": "61",
          "敗戦": "66",
          "ホールド": "99",
          "HP": "121",
          "セーブ": "22",
          "勝率": "0.480",
          "投球回": "1135.8",
          "打者": "5032",
          "被安打": "1127",
          "被本塁打": "110",
          "奪三振": "963",
          "奪三振率": "7.62",
          "与四球": "477",
          "与死球": "37",
          "暴投": "33",
          "ボーク": "1",
          "失点": "539",
          "自責点": "461"
        },
        "熊本": {
          "防御率": "4.50",
          "登板": "9",
          "完投": "0",
          "完封": "0",
          "無四球": "0",
          "勝利": "1",
          "敗戦": "1",
          "ホールド": "3",
          "HP": "4",
          "セーブ": "1",
          "勝率": "0.500",
          "投球回": "17.3",
          "打者": "74",
          "被安打": "14",
          "被本塁打": "2",
          "奪三振": "17",
          "奪三振率": "8.50",
          "与四球": "8",
          "与死球": "2",
          "暴投": "1",
          "ボーク": "0",
          "失点": "9",
          "自責点": "9"
        },
        "楽天生命パーク": {
          "防御率": "3.65",
          "登板": "34",
          "完投": "1",
          "完封": "1",
          "無四球": "1",
          "勝利": "5",
          "敗戦": "3",
          "ホールド": "7",
          "HP": "9",
          "セーブ": "3",
          "勝率": "0.625",
          "投球回": "65.5",
          "打者": "292",
          "被安打": "63",
          "被本塁打": "9",
          "奪三振": "61",
          "奪三振率": "8.24",
          "与四球": "27",
          "与死球": "6",
          "暴投": "1",
          "ボーク": "0",
          "失点": "30",
          "自責点": "27"
        },
        "メットライフ": {
          "防御率": "4.90",
          "登板": "33",
          "完投": "0",
          "完封": "0",
          "無四球": "0",
          "勝利": "4",
          "敗戦": "5",
          "ホールド": "7",
          "HP": "9",
          "セーブ": "1",
          "勝率": "0.444",
          "投球回": "76.9",
          "打者": "353",
          "被安打": "85",
          "被本塁打": "10",
          "奪三振": "60",
          "奪三振率": "6.84",
          "与四球": "32",
          "与死球": "8",
          "暴投": "1",
          "ボーク": "0",
          "失点": "51",
          "自責点": "43"
        },
        "岐阜": {
          "防御率": "4.50",
          "登板": "11",
          "完投": "0",
          "完封": "0",
          "無四球": "0",
          "勝利": "1",
          "敗戦": "1",
          "ホールド": "0",
          "HP": "0",
          "セーブ": "0",
          "勝率": "0.500",
          "投球回": "17.3",
          "打者": "80",
          "被安打": "19",
          "被本塁打": "1",
          "奪三振": "16",
          "奪三振率": "8.00",
          "与四球": "10",
          "与死球": "1",
          "暴投": "1",
          "ボーク": "0",
          "失点": "9",
          "自責点": "9"
        },
        "長野": {
          "防御率": "3.68",
          "登板": "15",
          "完投": "0",
          "完封": "0",
          "無四球": "0",
          "勝利": "1",
          "敗戦": "1",
          "ホールド": "5",
          "HP": "6",
          "セーブ": "1",
          "勝率": "0.500",
          "投球回": "20.6",
          "打者": "102",
          "被安打": "26",
          "被本塁打": "2",
          "奪三振": "24",
          "奪三振率": "9.82",
          "与四球": "10",
          "与死球": "2",
          "暴投": "0",
          "ボーク": "0",
          "失点": "11",
          "自責点": "9"
        },
        "前橋": {
          "防御率": "6.00",
          "登板": "11",
          "完投": "0",
          "完封": "0",
          "無四球": "0",
          "勝利": "1",
          "敗戦": "1",
          "ホールド": "2",
          "HP": "2",
          "セーブ": "0",
          "勝率": "0.500",
          "投球回": "16.6",
          "打者": "80",
          "被安打": "23",
          "被本塁打": "2",
          "奪三振": "18",
          "奪三振率": "9.00",
          "与四球": "3",
          "与死球": "1",
          "暴投": "0",
          "ボーク": "0",
          "失点": "12",
          "自責点": "12"
        },
        "新潟": {
          "防御率": "4.50",
          "登板": "22",
          "完投": "0",
          "完封": "0",
          "無四球": "0",
          "勝利": "2",
          "敗戦": "2",
          "ホールド": "5",
          "HP": "5",
          "セーブ": "2",
          "勝率": "0.500",
          "投球回": "33.9",
          "打者": "159",
          "被安打": "41",
          "被本塁打": "3",
          "奪三振": "29",
          "奪三振率": "7.25",
          "与四球": "11",
          "与死球": "0",
          "暴投": "0",
          "ボーク": "0",
          "失点": "20",
          "自責点": "18"
        },
        "郡山": {
          "防御率": "3.38",
          "登板": "3",
          "完投": "0",
          "完封": "0",
          "無四球": "0",
          "勝利": "0",
          "敗戦": "1",
          "ホールド": "0",
          "HP": "0",
          "セーブ": "0",
          "勝率": "0.000",
          "投球回": "7.3",
          "打者": "36",
          "被安打": "8",
          "被本塁打": "0",
          "奪三振": "9",
          "奪三振率": "10.13",
          "与四球": "4",
          "与死球": "0",
          "暴投": "0",
          "ボーク": "0",
          "失点": "3",
          "自責点": "3"
        },
        "松山": {
          "防御率": "7.41",
          "登板": "6",
          "完投": "1",
          "完封": "0",
          "無四球": "0",
          "勝利": "1",
          "敗戦": "1",
          "ホールド": "0",
          "HP": "0",
          "セーブ": "0",
          "勝率": "0.500",
          "投球回": "16.3",
          "打者": "80",
          "被安打": "23",
          "被本塁打": "3",
          "奪三振": "13",
          "奪三振率": "6.88",
          "与四球": "7",
          "与死球": "2",
          "暴投": "0",
          "ボーク": "0",
          "失点": "14",
          "自責点": "14"
        },
        "ＺＯＺＯマリン": {
          "防御率": "3.84",
          "登板": "35",
          "完投": "1",
          "完封": "0",
          "無四球": "0",
          "勝利": "6",
          "敗戦": "3",
          "ホールド": "8",
          "HP": "10",
          "セーブ": "4",
          "勝率": "0.667",
          "投球回": "77.8",
          "打者": "345",
          "被安打": "68",
          "被本塁打": "9",
          "奪三振": "73",
          "奪三振率": "8.25",
          "与四球": "36",
          "与死球": "5",
          "暴投": "4",
          "ボーク": "0",
          "失点": "35",
          "自責点": "34"
        },
        "ヤフオクドーム": {
          "防御率": "3.73",
          "登板": "36",
          "完投": "0",
          "完封": "0",
          "無四球": "0",
          "勝利": "2",
          "敗戦": "5",
          "ホールド": "10",
          "HP": "10",
          "セーブ": "1",
          "勝率": "0.286",
          "投球回": "77.8",
          "打者": "322",
          "被安打": "60",
          "被本塁打": "19",
          "奪三振": "76",
          "奪三振率": "8.59",
          "与四球": "25",
          "与死球": "1",
          "暴投": "3",
          "ボーク": "0",
          "失点": "34",
          "自責点": "33"
        },
        "豊橋": {
          "防御率": "5.29",
          "登板": "9",
          "完投": "0",
          "完封": "0",
          "無四球": "0",
          "勝利": "1",
          "敗戦": "1",
          "ホールド": "2",
          "HP": "3",
          "セーブ": "1",
          "勝率": "0.500",
          "投球回": "16.3",
          "打者": "72",
          "被安打": "21",
          "被本塁打": "3",
          "奪三振": "18",
          "奪三振率": "9.53",
          "与四球": "2",
          "与死球": "0",
          "暴投": "0",
          "ボーク": "0",
          "失点": "10",
          "自責点": "10"
        },
        "三次": {
          "防御率": "2.65",
          "登板": "6",
          "完投": "0",
          "完封": "0",
          "無四球": "0",
          "勝利": "1",
          "敗戦": "1",
          "ホールド": "1",
          "HP": "1",
          "セーブ": "1",
          "勝率": "0.500",
          "投球回": "17",
          "打者": "71",
          "被安打": "16",
          "被本塁打": "1",
          "奪三振": "9",
          "奪三振率": "4.76",
          "与四球": "3",
          "与死球": "1",
          "暴投": "0",
          "ボーク": "0",
          "失点": "5",
          "自責点": "5"
        },
        "倉敷": {
          "防御率": "4.00",
          "登板": "4",
          "完投": "0",
          "完封": "0",
          "無四球": "0",
          "勝利": "0",
          "敗戦": "1",
          "ホールド": "0",
          "HP": "0",
          "セーブ": "0",
          "勝率": "0.000",
          "投球回": "8.3",
          "打者": "39",
          "被安打": "7",
          "被本塁打": "1",
          "奪三振": "6",
          "奪三振率": "6.00",
          "与四球": "5",
          "与死球": "1",
          "暴投": "0",
          "ボーク": "0",
          "失点": "5",
          "自責点": "4"
        }
      },
      "故意四球": "189",
      "QS率": "44.4",
      "BABIP": ".303",
      "BB/9": "3.36",
      "HR/9": "1.01",
      "K%": "20.2",
      "BB%": "8.7",
      "HR%": "2.60",
      "K-BB%": "11.6",
      "LOB%": "73.7",
      "小松式ドネーション": "35434000",
      "ONE OUTS(万)": "-6623000"
    },
    "Pacific": {
      "防御率": "3.91",
      "登板": "3706",
      "先発": "835",
      "完投": "18",
      "完封": "10",
      "無四球": "3",
      "QS": "338",
      "交代完了": "823",
      "勝利": "417",
      "敗戦": "400",
      "ホールド": "745",
      "HP": "893",
      "セーブ": "225",
      "勝率": "0.510",
      "投球回": "7464.7",
      "打者": "32006",
      "被安打": "7044",
      "被本塁打": "819",
      "奪三振": "6233",
      "奪三振率": "7.51",
      "与四球": "2827",
      "与死球": "336",
      "暴投": "233",
      "ボーク": "18",
      "失点": "3579",
      "自責点": "3245",
      "被打率": "0.251",
      "K/BB": "2.20",
      "WHIP": "1.32",
      "アウト": "22497.0",
      "対右": {
        "被打率": "0.247",
        "被打数": "14244",
        "被安打": "3517",
        "被本塁打": "546",
        "奪三振": "3356",
        "与四球": "1400",
        "与死球": "187"
      },
      "対左": {
        "被打率": "0.254",
        "被打数": "13869",
        "被安打": "3527",
        "被本塁打": "273",
        "奪三振": "2877",
        "与四球": "1427",
        "与死球": "149"
      },
      "被打数": "28113",
      "球場": {
        "東京ドーム": {
          "防御率": "4.50",
          "登板": "160",
          "完投": "0",
          "完封": "0",
          "無四球": "0",
          "勝利": "17",
          "敗戦": "18",
          "ホールド": "33",
          "HP": "42",
          "セーブ": "7",
          "勝率": "0.486",
          "投球回": "306.5",
          "打者": "1355",
          "被安打": "305",
          "被本塁打": "41",
          "奪三振": "305",
          "奪三振率": "8.92",
          "与四球": "121",
          "与死球": "13",
          "暴投": "5",
          "ボーク": "1",
          "失点": "156",
          "自責点": "154"
        },
        "ナゴヤドーム": {
          "防御率": "4.21",
          "登板": "37",
          "完投": "0",
          "完封": "0",
          "無四球": "0",
          "勝利": "5",
          "敗戦": "4",
          "ホールド": "5",
          "HP": "6",
          "セーブ": "4",
          "勝率": "0.556",
          "投球回": "75.6",
          "打者": "331",
          "被安打": "83",
          "被本塁打": "3",
          "奪三振": "59",
          "奪三振率": "6.90",
          "与四球": "23",
          "与死球": "3",
          "暴投": "1",
          "ボーク": "0",
          "失点": "39",
          "自責点": "36"
        },
        "メットライフ": {
          "防御率": "4.77",
          "登板": "538",
          "完投": "4",
          "完封": "3",
          "無四球": "0",
          "勝利": "62",
          "敗戦": "60",
          "ホールド": "82",
          "HP": "104",
          "セーブ": "23",
          "勝率": "0.508",
          "投球回": "1071.4",
          "打者": "4816",
          "被安打": "1122",
          "被本塁打": "142",
          "奪三振": "797",
          "奪三振率": "6.69",
          "与四球": "475",
          "与死球": "58",
          "暴投": "38",
          "ボーク": "3",
          "失点": "635",
          "自責点": "568"
        },
        "ＺＯＺＯマリン": {
          "防御率": "3.75",
          "登板": "559",
          "完投": "2",
          "完封": "1",
          "無四球": "1",
          "勝利": "62",
          "敗戦": "65",
          "ホールド": "107",
          "HP": "132",
          "セーブ": "34",
          "勝率": "0.488",
          "投球回": "1156.3",
          "打者": "4984",
          "被安打": "1077",
          "被本塁打": "135",
          "奪三振": "963",
          "奪三振率": "7.49",
          "与四球": "425",
          "与死球": "70",
          "暴投": "43",
          "ボーク": "3",
          "失点": "547",
          "自責点": "482"
        },
        "京セラＤ大阪": {
          "防御率": "3.57",
          "登板": "470",
          "完投": "1",
          "完封": "1",
          "無四球": "0",
          "勝利": "52",
          "敗戦": "48",
          "ホールド": "93",
          "HP": "109",
          "セーブ": "29",
          "勝率": "0.520",
          "投球回": "947.6",
          "打者": "4074",
          "被安打": "881",
          "被本塁打": "72",
          "奪三振": "787",
          "奪三振率": "7.46",
          "与四球": "358",
          "与死球": "36",
          "暴投": "35",
          "ボーク": "4",
          "失点": "416",
          "自責点": "376"
        },
        "ヤフオクドーム": {
          "防御率": "4.03",
          "登板": "497",
          "完投": "2",
          "完封": "2",
          "無四球": "0",
          "勝利": "60",
          "敗戦": "56",
          "ホールド": "101",
          "HP": "118",
          "セーブ": "31",
          "勝率": "0.517",
          "投球回": "1040.3",
          "打者": "4465",
          "被安打": "965",
          "被本塁打": "152",
          "奪三振": "912",
          "奪三振率": "7.88",
          "与四球": "378",
          "与死球": "50",
          "暴投": "23",
          "ボーク": "3",
          "失点": "501",
          "自責点": "466"
        },
        "盛岡": {
          "防御率": "4.24",
          "登板": "7",
          "完投": "0",
          "完封": "0",
          "無四球": "0",
          "勝利": "1",
          "敗戦": "1",
          "ホールド": "1",
          "HP": "1",
          "セーブ": "0",
          "勝率": "0.500",
          "投球回": "16.3",
          "打者": "67",
          "被安打": "11",
          "被本塁打": "4",
          "奪三振": "18",
          "奪三振率": "9.53",
          "与四球": "7",
          "与死球": "1",
          "暴投": "0",
          "ボーク": "0",
          "失点": "9",
          "自責点": "8"
        },
        "札幌ドーム": {
          "防御率": "3.82",
          "登板": "458",
          "完投": "4",
          "完封": "3",
          "無四球": "1",
          "勝利": "49",
          "敗戦": "48",
          "ホールド": "97",
          "HP": "112",
          "セーブ": "30",
          "勝率": "0.505",
          "投球回": "890.4",
          "打者": "3804",
          "被安打": "833",
          "被本塁打": "68",
          "奪三振": "744",
          "奪三振率": "7.51",
          "与四球": "317",
          "与死球": "27",
          "暴投": "25",
          "ボーク": "1",
          "失点": "402",
          "自責点": "378"
        },
        "楽天生命パーク": {
          "防御率": "3.54",
          "登板": "542",
          "完投": "5",
          "完封": "0",
          "無四球": "1",
          "勝利": "58",
          "敗戦": "59",
          "ホールド": "135",
          "HP": "164",
          "セーブ": "35",
          "勝率": "0.496",
          "投球回": "1047.8",
          "打者": "4524",
          "被安打": "959",
          "被本塁打": "109",
          "奪三振": "953",
          "奪三振率": "8.17",
          "与四球": "418",
          "与死球": "43",
          "暴投": "33",
          "ボーク": "0",
          "失点": "459",
          "自責点": "413"
        },
        "横浜": {
          "防御率": "4.54",
          "登板": "39",
          "完投": "0",
          "完封": "0",
          "無四球": "0",
          "勝利": "3",
          "敗戦": "6",
          "ホールド": "8",
          "HP": "10",
          "セーブ": "1",
          "勝率": "0.333",
          "投球回": "72.4",
          "打者": "319",
          "被安打": "67",
          "被本塁打": "10",
          "奪三振": "66",
          "奪三振率": "8.10",
          "与四球": "27",
          "与死球": "2",
          "暴投": "5",
          "ボーク": "0",
          "失点": "37",
          "自責点": "37"
        },
        "甲子園": {
          "防御率": "3.33",
          "登板": "38",
          "完投": "0",
          "完封": "0",
          "無四球": "0",
          "勝利": "5",
          "敗戦": "3",
          "ホールド": "12",
          "HP": "13",
          "セーブ": "2",
          "勝率": "0.625",
          "投球回": "66.5",
          "打者": "303",
          "被安打": "73",
          "被本塁打": "3",
          "奪三振": "51",
          "奪三振率": "6.78",
          "与四球": "16",
          "与死球": "5",
          "暴投": "2",
          "ボーク": "0",
          "失点": "28",
          "自責点": "25"
        },
        "北九州": {
          "防御率": "3.75",
          "登板": "19",
          "完投": "0",
          "完封": "0",
          "無四球": "0",
          "勝利": "2",
          "敗戦": "2",
          "ホールド": "0",
          "HP": "0",
          "セーブ": "1",
          "勝率": "0.500",
          "投球回": "33.9",
          "打者": "162",
          "被安打": "34",
          "被本塁打": "5",
          "奪三振": "32",
          "奪三振率": "8.00",
          "与四球": "21",
          "与死球": "2",
          "暴投": "1",
          "ボーク": "2",
          "失点": "22",
          "自責点": "15"
        },
        "前橋": {
          "防御率": "6.00",
          "登板": "7",
          "完投": "0",
          "完封": "0",
          "無四球": "0",
          "勝利": "1",
          "敗戦": "1",
          "ホールド": "0",
          "HP": "0",
          "セーブ": "0",
          "勝率": "0.500",
          "投球回": "18",
          "打者": "84",
          "被安打": "18",
          "被本塁打": "4",
          "奪三振": "14",
          "奪三振率": "7.00",
          "与四球": "8",
          "与死球": "3",
          "暴投": "0",
          "ボーク": "0",
          "失点": "13",
          "自責点": "12"
        },
        "那覇": {
          "防御率": "5.03",
          "登板": "16",
          "完投": "0",
          "完封": "0",
          "無四球": "0",
          "勝利": "2",
          "敗戦": "2",
          "ホールド": "1",
          "HP": "1",
          "セーブ": "1",
          "勝率": "0.500",
          "投球回": "31.9",
          "打者": "164",
          "被安打": "43",
          "被本塁打": "3",
          "奪三振": "37",
          "奪三振率": "9.79",
          "与四球": "18",
          "与死球": "1",
          "暴投": "1",
          "ボーク": "0",
          "失点": "23",
          "自責点": "19"
        },
        "ほっと神戸": {
          "防御率": "4.58",
          "登板": "109",
          "完投": "0",
          "完封": "0",
          "無四球": "0",
          "勝利": "11",
          "敗戦": "11",
          "ホールド": "19",
          "HP": "22",
          "セーブ": "7",
          "勝率": "0.500",
          "投球回": "184.8",
          "打者": "854",
          "被安打": "204",
          "被本塁打": "27",
          "奪三振": "162",
          "奪三振率": "7.81",
          "与四球": "62",
          "与死球": "5",
          "暴投": "5",
          "ボーク": "0",
          "失点": "109",
          "自責点": "95"
        },
        "弘前": {
          "防御率": "1.50",
          "登板": "8",
          "完投": "0",
          "完封": "0",
          "無四球": "0",
          "勝利": "1",
          "敗戦": "0",
          "ホールド": "3",
          "HP": "3",
          "セーブ": "1",
          "勝率": "1.000",
          "投球回": "11.3",
          "打者": "54",
          "被安打": "10",
          "被本塁打": "0",
          "奪三振": "11",
          "奪三振率": "8.25",
          "与四球": "7",
          "与死球": "1",
          "暴投": "0",
          "ボーク": "0",
          "失点": "2",
          "自責点": "2"
        },
        "県営大宮": {
          "防御率": "5.43",
          "登板": "37",
          "完投": "0",
          "完封": "0",
          "無四球": "0",
          "勝利": "3",
          "敗戦": "3",
          "ホールド": "11",
          "HP": "13",
          "セーブ": "2",
          "勝率": "0.500",
          "投球回": "59.2",
          "打者": "283",
          "被安打": "69",
          "被本塁打": "7",
          "奪三振": "46",
          "奪三振率": "6.94",
          "与四球": "31",
          "与死球": "4",
          "暴投": "2",
          "ボーク": "1",
          "失点": "40",
          "自責点": "36"
        },
        "帯広": {
          "防御率": "2.50",
          "登板": "8",
          "完投": "0",
          "完封": "0",
          "無四球": "0",
          "勝利": "1",
          "敗戦": "1",
          "ホールド": "2",
          "HP": "2",
          "セーブ": "1",
          "勝率": "0.500",
          "投球回": "17.3",
          "打者": "73",
          "被安打": "17",
          "被本塁打": "3",
          "奪三振": "14",
          "奪三振率": "7.00",
          "与四球": "2",
          "与死球": "1",
          "暴投": "1",
          "ボーク": "0",
          "失点": "7",
          "自責点": "5"
        },
        "釧路": {
          "防御率": "6.98",
          "登板": "19",
          "完投": "0",
          "完封": "0",
          "無四球": "0",
          "勝利": "2",
          "敗戦": "2",
          "ホールド": "1",
          "HP": "2",
          "セーブ": "1",
          "勝率": "0.500",
          "投球回": "29.2",
          "打者": "151",
          "被安打": "44",
          "被本塁打": "4",
          "奪三振": "20",
          "奪三振率": "6.07",
          "与四球": "14",
          "与死球": "2",
          "暴投": "2",
          "ボーク": "0",
          "失点": "28",
          "自責点": "23"
        },
        "熊本": {
          "防御率": "0.53",
          "登板": "5",
          "完投": "0",
          "完封": "0",
          "無四球": "0",
          "勝利": "1",
          "敗戦": "1",
          "ホールド": "1",
          "HP": "1",
          "セーブ": "1",
          "勝率": "0.500",
          "投球回": "17",
          "打者": "68",
          "被安打": "12",
          "被本塁打": "0",
          "奪三振": "18",
          "奪三振率": "9.53",
          "与四球": "8",
          "与死球": "0",
          "暴投": "1",
          "ボーク": "0",
          "失点": "3",
          "自責点": "1"
        },
        "長崎": {
          "防御率": "2.30",
          "登板": "12",
          "完投": "0",
          "完封": "0",
          "無四球": "0",
          "勝利": "0",
          "敗戦": "0",
          "ホールド": "4",
          "HP": "4",
          "セーブ": "0",
          "勝率": "0.000",
          "投球回": "14.5",
          "打者": "82",
          "被安打": "11",
          "被本塁打": "0",
          "奪三振": "20",
          "奪三振率": "11.49",
          "与四球": "12",
          "与死球": "2",
          "暴投": "1",
          "ボーク": "0",
          "失点": "6",
          "自責点": "4"
        },
        "旭川": {
          "防御率": "3.94",
          "登板": "19",
          "完投": "0",
          "完封": "0",
          "無四球": "0",
          "勝利": "2",
          "敗戦": "2",
          "ホールド": "3",
          "HP": "3",
          "セーブ": "1",
          "勝率": "0.500",
          "投球回": "29.2",
          "打者": "137",
          "被安打": "38",
          "被本塁打": "5",
          "奪三振": "21",
          "奪三振率": "6.37",
          "与四球": "6",
          "与死球": "1",
          "暴投": "0",
          "ボーク": "0",
          "失点": "16",
          "自責点": "13"
        },
        "鹿児島": {
          "防御率": "4.50",
          "登板": "5",
          "完投": "0",
          "完封": "0",
          "無四球": "0",
          "勝利": "1",
          "敗戦": "1",
          "ホールド": "0",
          "HP": "0",
          "セーブ": "1",
          "勝率": "0.500",
          "投球回": "10",
          "打者": "46",
          "被安打": "13",
          "被本塁打": "3",
          "奪三振": "4",
          "奪三振率": "3.60",
          "与四球": "3",
          "与死球": "0",
          "暴投": "0",
          "ボーク": "0",
          "失点": "6",
          "自責点": "5"
        },
        "マツダスタジアム": {
          "防御率": "3.02",
          "登板": "42",
          "完投": "0",
          "完封": "0",
          "無四球": "0",
          "勝利": "7",
          "敗戦": "2",
          "ホールド": "11",
          "HP": "14",
          "セーブ": "5",
          "勝率": "0.778",
          "投球回": "80.1",
          "打者": "342",
          "被安打": "71",
          "被本塁打": "7",
          "奪三振": "72",
          "奪三振率": "8.07",
          "与四球": "27",
          "与死球": "2",
          "暴投": "2",
          "ボーク": "0",
          "失点": "29",
          "自責点": "27"
        },
        "神宮": {
          "防御率": "4.50",
          "登板": "42",
          "完投": "0",
          "完封": "0",
          "無四球": "0",
          "勝利": "6",
          "敗戦": "3",
          "ホールド": "11",
          "HP": "12",
          "セーブ": "4",
          "勝率": "0.667",
          "投球回": "75.9",
          "打者": "332",
          "被安打": "61",
          "被本塁打": "10",
          "奪三振": "76",
          "奪三振率": "8.77",
          "与四球": "40",
          "与死球": "3",
          "暴投": "5",
          "ボーク": "0",
          "失点": "40",
          "自責点": "39"
        },
        "郡山": {
          "防御率": "1.00",
          "登板": "3",
          "完投": "0",
          "完封": "0",
          "無四球": "0",
          "勝利": "1",
          "敗戦": "0",
          "ホールド": "1",
          "HP": "1",
          "セーブ": "1",
          "勝率": "1.000",
          "投球回": "9",
          "打者": "34",
          "被安打": "6",
          "被本塁打": "1",
          "奪三振": "6",
          "奪三振率": "6.00",
          "与四球": "2",
          "与死球": "1",
          "暴投": "0",
          "ボーク": "0",
          "失点": "1",
          "自責点": "1"
        },
        "倉敷": {
          "防御率": "3.00",
          "登板": "5",
          "完投": "0",
          "完封": "0",
          "無四球": "0",
          "勝利": "1",
          "敗戦": "0",
          "ホールド": "2",
          "HP": "3",
          "セーブ": "1",
          "勝率": "1.000",
          "投球回": "9",
          "打者": "35",
          "被安打": "9",
          "被本塁打": "1",
          "奪三振": "11",
          "奪三振率": "11.00",
          "与四球": "0",
          "与死球": "0",
          "暴投": "1",
          "ボーク": "0",
          "失点": "3",
          "自責点": "3"
        },
        "山形市": {
          "防御率": "1.00",
          "登板": "5",
          "完投": "0",
          "完封": "0",
          "無四球": "0",
          "勝利": "1",
          "敗戦": "1",
          "ホールド": "1",
          "HP": "1",
          "セーブ": "1",
          "勝率": "0.500",
          "投球回": "18",
          "打者": "63",
          "被安打": "8",
          "被本塁打": "0",
          "奪三振": "14",
          "奪三振率": "7.00",
          "与四球": "1",
          "与死球": "0",
          "暴投": "1",
          "ボーク": "0",
          "失点": "2",
          "自責点": "2"
        }
      },
      "故意四球": "104",
      "QS率": "40.5",
      "BABIP": ".296",
      "BB/9": "3.41",
      "HR/9": "0.99",
      "K%": "19.5",
      "BB%": "8.8",
      "HR%": "2.56",
      "K-BB%": "10.6",
      "LOB%": "73.2",
      "小松式ドネーション": "36367000",
      "ONE OUTS(万)": "-6646500"
    }
  },
  "Hitter": {
    "Central": {
      "打率": "0.260",
      "試合": "10043",
      "打席": "30669",
      "打数": "27109",
      "安打": "7055",
      "二塁打": "1273",
      "三塁打": "116",
      "本塁打": "828",
      "塁打": "11044",
      "打点": "3355",
      "得点": "3508",
      "三振": "5845",
      "四球": "2734",
      "死球": "273",
      "犠打": "383",
      "犠飛": "170",
      "盗塁": "425",
      "盗塁死": "181",
      "併殺打": "577",
      "出塁率": "0.332",
      "長打率": "0.407",
      "OPS": "0.740",
      "失策": "403",
      "圏打率": "0.264",
      "圏打席": "8046",
      "圏打数": "6632",
      "圏安打": "1753",
      "圏本塁打": "177",
      "圏打点": "2433",
      "圏三振": "1420",
      "圏四球": "1036",
      "圏死球": "82",
      "圏犠打": "126",
      "圏犠飛": "170",
      "対右": {
        "打率": "0.266",
        "打数": "17395",
        "安打": "4626",
        "本塁打": "506",
        "打点": "2250",
        "三振": "3614",
        "四球": "1754",
        "死球": "176",
        "犠打": "241",
        "犠飛": "118"
      },
      "対左": {
        "打率": "0.250",
        "打数": "9705",
        "安打": "2428",
        "本塁打": "322",
        "打点": "1105",
        "三振": "2227",
        "四球": "980",
        "死球": "97",
        "犠打": "141",
        "犠飛": "52"
      },
      "球場": {
        "東京ドーム": {
          "打率": "0.266",
          "試合": "1431",
          "打数": "3728",
          "安打": "992",
          "本塁打": "172",
          "打点": "527",
          "三振": "850",
          "四球": "408",
          "死球": "46",
          "犠打": "55",
          "犠飛": "20",
          "盗塁": "67"
        },
        "神宮": {
          "打率": "0.268",
          "試合": "1500",
          "打数": "4004",
          "安打": "1075",
          "本塁打": "173",
          "打点": "593",
          "三振": "925",
          "四球": "419",
          "死球": "37",
          "犠打": "52",
          "犠飛": "27",
          "盗塁": "68"
        },
        "ナゴヤドーム": {
          "打率": "0.251",
          "試合": "1542",
          "打数": "4150",
          "安打": "1042",
          "本塁打": "69",
          "打点": "442",
          "三振": "870",
          "四球": "338",
          "死球": "47",
          "犠打": "53",
          "犠飛": "29",
          "盗塁": "72"
        },
        "マツダスタジアム": {
          "打率": "0.261",
          "試合": "1523",
          "打数": "4142",
          "安打": "1082",
          "本塁打": "110",
          "打点": "479",
          "三振": "842",
          "四球": "457",
          "死球": "34",
          "犠打": "68",
          "犠飛": "30",
          "盗塁": "51"
        },
        "横浜": {
          "打率": "0.259",
          "試合": "1560",
          "打数": "4179",
          "安打": "1083",
          "本塁打": "152",
          "打点": "538",
          "三振": "904",
          "四球": "436",
          "死球": "32",
          "犠打": "51",
          "犠飛": "28",
          "盗塁": "50"
        },
        "甲子園": {
          "打率": "0.264",
          "試合": "1283",
          "打数": "3537",
          "安打": "932",
          "本塁打": "71",
          "打点": "369",
          "三振": "697",
          "四球": "338",
          "死球": "41",
          "犠打": "55",
          "犠飛": "14",
          "盗塁": "71"
        },
        "メットライフ": {
          "打率": "0.248",
          "試合": "111",
          "打数": "314",
          "安打": "78",
          "本塁打": "10",
          "打点": "44",
          "三振": "65",
          "四球": "37",
          "死球": "4",
          "犠打": "6",
          "犠飛": "2",
          "盗塁": "4"
        },
        "京セラＤ大阪": {
          "打率": "0.246",
          "試合": "368",
          "打数": "987",
          "安打": "243",
          "本塁打": "13",
          "打点": "115",
          "三振": "229",
          "四球": "112",
          "死球": "6",
          "犠打": "15",
          "犠飛": "8",
          "盗塁": "9"
        },
        "岐阜": {
          "打率": "0.288",
          "試合": "26",
          "打数": "66",
          "安打": "19",
          "本塁打": "1",
          "打点": "9",
          "三振": "15",
          "四球": "9",
          "死球": "1",
          "犠打": "0",
          "犠飛": "0",
          "盗塁": "2"
        },
        "鹿児島": {
          "打率": "0.224",
          "試合": "23",
          "打数": "58",
          "安打": "13",
          "本塁打": "3",
          "打点": "9",
          "三振": "18",
          "四球": "9",
          "死球": "1",
          "犠打": "0",
          "犠飛": "2",
          "盗塁": "0"
        },
        "熊本": {
          "打率": "0.250",
          "試合": "26",
          "打数": "60",
          "安打": "15",
          "本塁打": "2",
          "打点": "9",
          "三振": "15",
          "四球": "9",
          "死球": "2",
          "犠打": "1",
          "犠飛": "0",
          "盗塁": "0"
        },
        "前橋": {
          "打率": "0.310",
          "試合": "26",
          "打数": "71",
          "安打": "22",
          "本塁打": "2",
          "打点": "10",
          "三振": "15",
          "四球": "3",
          "死球": "1",
          "犠打": "0",
          "犠飛": "1",
          "盗塁": "1"
        },
        "長野": {
          "打率": "0.296",
          "試合": "28",
          "打数": "81",
          "安打": "24",
          "本塁打": "2",
          "打点": "10",
          "三振": "23",
          "四球": "10",
          "死球": "2",
          "犠打": "3",
          "犠飛": "1",
          "盗塁": "1"
        },
        "札幌ドーム": {
          "打率": "0.227",
          "試合": "107",
          "打数": "317",
          "安打": "72",
          "本塁打": "6",
          "打点": "34",
          "三振": "71",
          "四球": "28",
          "死球": "3",
          "犠打": "5",
          "犠飛": "4",
          "盗塁": "9"
        },
        "楽天生命パーク": {
          "打率": "0.235",
          "試合": "99",
          "打数": "272",
          "安打": "64",
          "本塁打": "8",
          "打点": "29",
          "三振": "74",
          "四球": "32",
          "死球": "1",
          "犠打": "3",
          "犠飛": "0",
          "盗塁": "6"
        },
        "秋田": {
          "打率": "0.274",
          "試合": "51",
          "打数": "135",
          "安打": "37",
          "本塁打": "3",
          "打点": "11",
          "三振": "27",
          "四球": "13",
          "死球": "3",
          "犠打": "2",
          "犠飛": "0",
          "盗塁": "1"
        },
        "新潟": {
          "打率": "0.297",
          "試合": "51",
          "打数": "138",
          "安打": "41",
          "本塁打": "3",
          "打点": "20",
          "三振": "25",
          "四球": "11",
          "死球": "0",
          "犠打": "4",
          "犠飛": "0",
          "盗塁": "2"
        },
        "郡山": {
          "打率": "0.194",
          "試合": "12",
          "打数": "31",
          "安打": "6",
          "本塁打": "1",
          "打点": "1",
          "三振": "6",
          "四球": "2",
          "死球": "1",
          "犠打": "0",
          "犠飛": "0",
          "盗塁": "0"
        },
        "松山": {
          "打率": "0.333",
          "試合": "23",
          "打数": "66",
          "安打": "22",
          "本塁打": "3",
          "打点": "14",
          "三振": "11",
          "四球": "7",
          "死球": "2",
          "犠打": "0",
          "犠飛": "0",
          "盗塁": "0"
        },
        "ＺＯＺＯマリン": {
          "打率": "0.277",
          "試合": "97",
          "打数": "311",
          "安打": "86",
          "本塁打": "9",
          "打点": "46",
          "三振": "68",
          "四球": "30",
          "死球": "3",
          "犠打": "4",
          "犠飛": "3",
          "盗塁": "8"
        },
        "ヤフオクドーム": {
          "打率": "0.205",
          "試合": "100",
          "打数": "302",
          "安打": "62",
          "本塁打": "10",
          "打点": "29",
          "三振": "62",
          "四球": "21",
          "死球": "5",
          "犠打": "5",
          "犠飛": "1",
          "盗塁": "1"
        },
        "豊橋": {
          "打率": "0.313",
          "試合": "21",
          "打数": "67",
          "安打": "21",
          "本塁打": "3",
          "打点": "10",
          "三振": "16",
          "四球": "2",
          "死球": "0",
          "犠打": "0",
          "犠飛": "0",
          "盗塁": "1"
        },
        "三次": {
          "打率": "0.246",
          "試合": "25",
          "打数": "61",
          "安打": "15",
          "本塁打": "1",
          "打点": "5",
          "三振": "8",
          "四球": "3",
          "死球": "1",
          "犠打": "0",
          "犠飛": "0",
          "盗塁": "0"
        },
        "倉敷": {
          "打率": "0.281",
          "試合": "10",
          "打数": "32",
          "安打": "9",
          "本塁打": "1",
          "打点": "2",
          "三振": "9",
          "四球": "0",
          "死球": "0",
          "犠打": "1",
          "犠飛": "0",
          "盗塁": "1"
        }
      },
      "故意四球": "186",
      "本塁打率": ".0305",
      "盗成功率": "70.1",
      "wOBA": ".324",
      "RC": "3703.67",
      "RC27": "4.68",
      "XR": "3685.85",
      "XR27": "4.66",
      "IsoP": ".147",
      "BB/K": "0.47",
      "BB%": "8.9",
      "K%": "19.1",
      "IsoD": ".072",
      "BABIP": ".302",
      "アダムダン率": "30.7",
      "ONE OUTS(万)": "-17910000"
    },
    "Pacific": {
      "打率": "0.253",
      "試合": "9992",
      "打席": "32181",
      "打数": "28227",
      "安打": "7147",
      "二塁打": "1188",
      "三塁打": "135",
      "本塁打": "840",
      "塁打": "11125",
      "打点": "3483",
      "得点": "3657",
      "三振": "6212",
      "四球": "2872",
      "死球": "352",
      "犠打": "536",
      "犠飛": "193",
      "盗塁": "534",
      "盗塁死": "254",
      "併殺打": "564",
      "出塁率": "0.328",
      "長打率": "0.394",
      "OPS": "0.722",
      "失策": "386",
      "圏打率": "0.264",
      "圏打席": "8397",
      "圏打数": "6906",
      "圏安打": "1824",
      "圏本塁打": "170",
      "圏打点": "2538",
      "圏三振": "1500",
      "圏四球": "1005",
      "圏死球": "128",
      "圏犠打": "165",
      "圏犠飛": "193",
      "対右": {
        "打率": "0.252",
        "打数": "21046",
        "安打": "5313",
        "本塁打": "640",
        "打点": "2598",
        "三振": "4629",
        "四球": "2161",
        "死球": "260",
        "犠打": "388",
        "犠飛": "145"
      },
      "球場": {
        "東京ドーム": {
          "打率": "0.258",
          "試合": "436",
          "打数": "1184",
          "安打": "305",
          "本塁打": "34",
          "打点": "145",
          "三振": "280",
          "四球": "118",
          "死球": "16",
          "犠打": "13",
          "犠飛": "6",
          "盗塁": "18"
        },
        "メットライフ": {
          "打率": "0.271",
          "試合": "1381",
          "打数": "4202",
          "安打": "1137",
          "本塁打": "143",
          "打点": "608",
          "三振": "799",
          "四球": "475",
          "死球": "62",
          "犠打": "67",
          "犠飛": "28",
          "盗塁": "103"
        },
        "ＺＯＺＯマリン": {
          "打率": "0.244",
          "試合": "1537",
          "打数": "4361",
          "安打": "1063",
          "本塁打": "137",
          "打点": "515",
          "三振": "961",
          "四球": "431",
          "死球": "72",
          "犠打": "88",
          "犠飛": "24",
          "盗塁": "80"
        },
        "ほっと神戸": {
          "打率": "0.264",
          "試合": "267",
          "打数": "770",
          "安打": "203",
          "本塁打": "27",
          "打点": "103",
          "三振": "161",
          "四球": "62",
          "死球": "5",
          "犠打": "9",
          "犠飛": "4",
          "盗塁": "14"
        },
        "ヤフオクドーム": {
          "打率": "0.245",
          "試合": "1426",
          "打数": "3927",
          "安打": "964",
          "本塁打": "161",
          "打点": "493",
          "三振": "925",
          "四球": "383",
          "死球": "46",
          "犠打": "77",
          "犠飛": "25",
          "盗塁": "73"
        },
        "県営大宮": {
          "打率": "0.290",
          "試合": "76",
          "打数": "238",
          "安打": "69",
          "本塁打": "7",
          "打点": "38",
          "三振": "46",
          "四球": "31",
          "死球": "4",
          "犠打": "8",
          "犠飛": "2",
          "盗塁": "4"
        },
        "札幌ドーム": {
          "打率": "0.244",
          "試合": "1230",
          "打数": "3422",
          "安打": "836",
          "本塁打": "68",
          "打点": "385",
          "三振": "759",
          "四球": "328",
          "死球": "27",
          "犠打": "58",
          "犠飛": "24",
          "盗塁": "52"
        },
        "楽天生命パーク": {
          "打率": "0.245",
          "試合": "1425",
          "打数": "4001",
          "安打": "982",
          "本塁打": "114",
          "打点": "457",
          "三振": "957",
          "四球": "422",
          "死球": "49",
          "犠打": "88",
          "犠飛": "29",
          "盗塁": "50"
        },
        "横浜": {
          "打率": "0.269",
          "試合": "101",
          "打数": "290",
          "安打": "78",
          "本塁打": "7",
          "打点": "39",
          "三振": "79",
          "四球": "33",
          "死球": "3",
          "犠打": "1",
          "犠飛": "2",
          "盗塁": "9"
        },
        "ナゴヤドーム": {
          "打率": "0.256",
          "試合": "106",
          "打数": "289",
          "安打": "74",
          "本塁打": "7",
          "打点": "38",
          "三振": "73",
          "四球": "24",
          "死球": "4",
          "犠打": "7",
          "犠飛": "1",
          "盗塁": "1"
        },
        "甲子園": {
          "打率": "0.306",
          "試合": "89",
          "打数": "271",
          "安打": "83",
          "本塁打": "6",
          "打点": "38",
          "三振": "44",
          "四球": "25",
          "死球": "1",
          "犠打": "4",
          "犠飛": "2",
          "盗塁": "4"
        },
        "京セラＤ大阪": {
          "打率": "0.249",
          "試合": "1306",
          "打数": "3592",
          "安打": "895",
          "本塁打": "71",
          "打点": "401",
          "三振": "780",
          "四球": "352",
          "死球": "39",
          "犠打": "83",
          "犠飛": "29",
          "盗塁": "81"
        },
        "弘前": {
          "打率": "0.239",
          "試合": "21",
          "打数": "67",
          "安打": "16",
          "本塁打": "1",
          "打点": "5",
          "三振": "14",
          "四球": "10",
          "死球": "1",
          "犠打": "1",
          "犠飛": "1",
          "盗塁": "2"
        },
        "北九州": {
          "打率": "0.252",
          "試合": "42",
          "打数": "135",
          "安打": "34",
          "本塁打": "5",
          "打点": "18",
          "三振": "32",
          "四球": "21",
          "死球": "2",
          "犠打": "2",
          "犠飛": "2",
          "盗塁": "5"
        },
        "釧路": {
          "打率": "0.336",
          "試合": "41",
          "打数": "131",
          "安打": "44",
          "本塁打": "4",
          "打点": "24",
          "三振": "20",
          "四球": "14",
          "死球": "2",
          "犠打": "2",
          "犠飛": "2",
          "盗塁": "4"
        },
        "前橋": {
          "打率": "0.250",
          "試合": "25",
          "打数": "72",
          "安打": "18",
          "本塁打": "4",
          "打点": "13",
          "三振": "14",
          "四球": "8",
          "死球": "3",
          "犠打": "1",
          "犠飛": "0",
          "盗塁": "2"
        },
        "盛岡": {
          "打率": "0.186",
          "試合": "22",
          "打数": "59",
          "安打": "11",
          "本塁打": "4",
          "打点": "7",
          "三振": "18",
          "四球": "7",
          "死球": "1",
          "犠打": "0",
          "犠飛": "0",
          "盗塁": "4"
        },
        "那覇": {
          "打率": "0.307",
          "試合": "47",
          "打数": "140",
          "安打": "43",
          "本塁打": "3",
          "打点": "20",
          "三振": "37",
          "四球": "18",
          "死球": "1",
          "犠打": "3",
          "犠飛": "2",
          "盗塁": "5"
        },
        "帯広": {
          "打率": "0.243",
          "試合": "23",
          "打数": "70",
          "安打": "17",
          "本塁打": "3",
          "打点": "6",
          "三振": "14",
          "四球": "2",
          "死球": "1",
          "犠打": "0",
          "犠飛": "0",
          "盗塁": "1"
        },
        "旭川": {
          "打率": "0.299",
          "試合": "47",
          "打数": "127",
          "安打": "38",
          "本塁打": "5",
          "打点": "16",
          "三振": "21",
          "四球": "6",
          "死球": "1",
          "犠打": "3",
          "犠飛": "0",
          "盗塁": "2"
        },
        "熊本": {
          "打率": "0.214",
          "試合": "24",
          "打数": "56",
          "安打": "12",
          "本塁打": "0",
          "打点": "2",
          "三振": "18",
          "四球": "8",
          "死球": "0",
          "犠打": "3",
          "犠飛": "1",
          "盗塁": "1"
        },
        "鹿児島": {
          "打率": "0.310",
          "試合": "20",
          "打数": "42",
          "安打": "13",
          "本塁打": "3",
          "打点": "5",
          "三振": "4",
          "四球": "3",
          "死球": "0",
          "犠打": "1",
          "犠飛": "0",
          "盗塁": "0"
        },
        "長崎": {
          "打率": "0.175",
          "試合": "25",
          "打数": "63",
          "安打": "11",
          "本塁打": "0",
          "打点": "6",
          "三振": "20",
          "四球": "12",
          "死球": "2",
          "犠打": "3",
          "犠飛": "2",
          "盗塁": "2"
        },
        "神宮": {
          "打率": "0.292",
          "試合": "112",
          "打数": "284",
          "安打": "83",
          "本塁打": "18",
          "打点": "48",
          "三振": "41",
          "四球": "38",
          "死球": "4",
          "犠打": "4",
          "犠飛": "3",
          "盗塁": "6"
        },
        "マツダスタジアム": {
          "打率": "0.303",
          "試合": "116",
          "打数": "314",
          "安打": "95",
          "本塁打": "7",
          "打点": "44",
          "三振": "67",
          "四球": "31",
          "死球": "5",
          "犠打": "7",
          "犠飛": "2",
          "盗塁": "9"
        },
        "郡山": {
          "打率": "0.258",
          "試合": "11",
          "打数": "31",
          "安打": "8",
          "本塁打": "0",
          "打点": "3",
          "三振": "9",
          "四球": "4",
          "死球": "0",
          "犠打": "1",
          "犠飛": "0",
          "盗塁": "0"
        },
        "倉敷": {
          "打率": "0.233",
          "試合": "12",
          "打数": "30",
          "安打": "7",
          "本塁打": "1",
          "打点": "4",
          "三振": "5",
          "四球": "5",
          "死球": "1",
          "犠打": "0",
          "犠飛": "1",
          "盗塁": "1"
        },
        "山形市": {
          "打率": "0.136",
          "試合": "24",
          "打数": "59",
          "安打": "8",
          "本塁打": "0",
          "打点": "2",
          "三振": "14",
          "四球": "1",
          "死球": "0",
          "犠打": "2",
          "犠飛": "1",
          "盗塁": "1"
        }
      },
      "故意四球": "111",
      "対左": {
        "打率": "0.256",
        "打数": "7142",
        "安打": "1829",
        "本塁打": "199",
        "打点": "882",
        "三振": "1575",
        "四球": "703",
        "死球": "92",
        "犠打": "146",
        "犠飛": "48"
      },
      "本塁打率": ".0298",
      "盗成功率": "67.8",
      "wOBA": ".318",
      "RC": "3713.48",
      "RC27": "4.43",
      "XR": "3735.64",
      "XR27": "4.46",
      "IsoP": ".141",
      "BB/K": "0.46",
      "BB%": "8.9",
      "K%": "19.3",
      "IsoD": ".075",
      "BABIP": ".295",
      "アダムダン率": "30.8",
      "ONE OUTS(万)": "-19080000"
    }
  }
}