{
  "Pitcher": {
    "Central": {
      "id": "182483472",
      "防御率": "3.85",
      "登板": "1252",
      "先発": "302",
      "完投": "18",
      "完封": "8",
      "無四球": "4",
      "QS": "141",
      "交代完了": "284",
      "勝利": "148",
      "敗戦": "148",
      "ホールド": "220",
      "HP": "266",
      "セーブ": "62",
      "勝率": "0.500",
      "投球回": "2677.0",
      "打者": "11631",
      "被安打": "2582",
      "被本塁打": "310",
      "奪三振": "2315",
      "奪三振率": "7.78",
      "与四球": "1053",
      "与死球": "89",
      "暴投": "64",
      "ボーク": "4",
      "失点": "1277",
      "自責点": "1146",
      "被打率": "0.253",
      "K/BB": "2.20",
      "WHIP": "1.36",
      "対右": {
        "被打率": "0.249",
        "被打数": "5525",
        "被安打": "1376",
        "被本塁打": "212",
        "奪三振": "1270",
        "与四球": "559",
        "与死球": "55"
      },
      "対左": {
        "被打率": "0.257",
        "被打数": "4698",
        "被安打": "1206",
        "被本塁打": "98",
        "奪三振": "1045",
        "与四球": "494",
        "与死球": "34"
      },
      "球場": {
        "東京ドーム": {
          "防御率": "5.14",
          "登板": "189",
          "完投": "1",
          "完封": "0",
          "無四球": "0",
          "勝利": "22",
          "敗戦": "22",
          "ホールド": "26",
          "HP": "34",
          "セーブ": "10",
          "勝率": "0.500",
          "投球回": "376.6",
          "打者": "1713",
          "被安打": "425",
          "被本塁打": "73",
          "奪三振": "346",
          "奪三振率": "8.24",
          "与四球": "150",
          "与死球": "17",
          "暴投": "5",
          "ボーク": "1",
          "失点": "232",
          "自責点": "216"
        },
        "神宮": {
          "防御率": "4.56",
          "登板": "236",
          "完投": "2",
          "完封": "1",
          "無四球": "0",
          "勝利": "24",
          "敗戦": "24",
          "ホールド": "48",
          "HP": "56",
          "セーブ": "12",
          "勝率": "0.500",
          "投球回": "465.7",
          "打者": "2094",
          "被安打": "464",
          "被本塁打": "78",
          "奪三振": "451",
          "奪三振率": "8.69",
          "与四球": "195",
          "与死球": "12",
          "暴投": "20",
          "ボーク": "0",
          "失点": "258",
          "自責点": "237"
        },
        "ナゴヤドーム": {
          "防御率": "3.43",
          "登板": "193",
          "完投": "4",
          "完封": "2",
          "無四球": "2",
          "勝利": "24",
          "敗戦": "24",
          "ホールド": "42",
          "HP": "49",
          "セーブ": "15",
          "勝率": "0.500",
          "投球回": "418.6",
          "打者": "1803",
          "被安打": "394",
          "被本塁打": "26",
          "奪三振": "376",
          "奪三振率": "8.06",
          "与四球": "140",
          "与死球": "17",
          "暴投": "13",
          "ボーク": "0",
          "失点": "169",
          "自責点": "160"
        },
        "鹿児島": {
          "防御率": "5.29",
          "登板": "8",
          "完投": "0",
          "完封": "0",
          "無四球": "0",
          "勝利": "1",
          "敗戦": "1",
          "ホールド": "0",
          "HP": "0",
          "セーブ": "0",
          "勝率": "0.500",
          "投球回": "17",
          "打者": "74",
          "被安打": "13",
          "被本塁打": "3",
          "奪三振": "20",
          "奪三振率": "10.59",
          "与四球": "9",
          "与死球": "1",
          "暴投": "2",
          "ボーク": "0",
          "失点": "10",
          "自責点": "10"
        },
        "マツダスタジアム": {
          "防御率": "3.40",
          "登板": "198",
          "完投": "4",
          "完封": "2",
          "無四球": "2",
          "勝利": "23",
          "敗戦": "23",
          "ホールド": "34",
          "HP": "42",
          "セーブ": "4",
          "勝率": "0.500",
          "投球回": "421.8",
          "打者": "1880",
          "被安打": "409",
          "被本塁打": "38",
          "奪三振": "342",
          "奪三振率": "7.27",
          "与四球": "187",
          "与死球": "15",
          "暴投": "8",
          "ボーク": "1",
          "失点": "196",
          "自責点": "160"
        },
        "横浜": {
          "防御率": "3.64",
          "登板": "161",
          "完投": "4",
          "完封": "2",
          "無四球": "0",
          "勝利": "21",
          "敗戦": "21",
          "ホールド": "18",
          "HP": "23",
          "セーブ": "8",
          "勝率": "0.500",
          "投球回": "359.6",
          "打者": "1559",
          "被安打": "332",
          "被本塁打": "46",
          "奪三振": "310",
          "奪三振率": "7.73",
          "与四球": "138",
          "与死球": "10",
          "暴投": "6",
          "ボーク": "0",
          "失点": "163",
          "自責点": "146"
        },
        "熊本": {
          "防御率": "4.50",
          "登板": "10",
          "完投": "0",
          "完封": "0",
          "無四球": "0",
          "勝利": "1",
          "敗戦": "1",
          "ホールド": "3",
          "HP": "4",
          "セーブ": "1",
          "勝率": "0.500",
          "投球回": "17.3",
          "打者": "76",
          "被安打": "15",
          "被本塁打": "2",
          "奪三振": "17",
          "奪三振率": "8.50",
          "与四球": "9",
          "与死球": "2",
          "暴投": "1",
          "ボーク": "0",
          "失点": "9",
          "自責点": "9"
        },
        "甲子園": {
          "防御率": "3.38",
          "登板": "210",
          "完投": "2",
          "完封": "1",
          "無四球": "0",
          "勝利": "26",
          "敗戦": "26",
          "ホールド": "36",
          "HP": "44",
          "セーブ": "8",
          "勝率": "0.500",
          "投球回": "454.5",
          "打者": "1987",
          "被安打": "444",
          "被本塁打": "38",
          "奪三振": "362",
          "奪三振率": "7.15",
          "与四球": "187",
          "与死球": "11",
          "暴投": "8",
          "ボーク": "0",
          "失点": "201",
          "自責点": "171"
        },
        "新潟": {
          "防御率": "6.00",
          "登板": "10",
          "完投": "0",
          "完封": "0",
          "無四球": "0",
          "勝利": "1",
          "敗戦": "1",
          "ホールド": "2",
          "HP": "2",
          "セーブ": "1",
          "勝率": "0.500",
          "投球回": "17.3",
          "打者": "81",
          "被安打": "19",
          "被本塁打": "1",
          "奪三振": "14",
          "奪三振率": "7.00",
          "与四球": "8",
          "与死球": "0",
          "暴投": "0",
          "ボーク": "0",
          "失点": "13",
          "自責点": "12"
        },
        "京セラＤ大阪": {
          "防御率": "0.96",
          "登板": "25",
          "完投": "0",
          "完封": "0",
          "無四球": "0",
          "勝利": "3",
          "敗戦": "3",
          "ホールド": "10",
          "HP": "11",
          "セーブ": "2",
          "勝率": "0.500",
          "投球回": "55.4",
          "打者": "213",
          "被安打": "28",
          "被本塁打": "1",
          "奪三振": "55",
          "奪三振率": "8.79",
          "与四球": "20",
          "与死球": "1",
          "暴投": "1",
          "ボーク": "2",
          "失点": "7",
          "自責点": "6"
        },
        "松山": {
          "防御率": "7.41",
          "登板": "6",
          "完投": "1",
          "完封": "0",
          "無四球": "0",
          "勝利": "1",
          "敗戦": "1",
          "ホールド": "0",
          "HP": "0",
          "セーブ": "0",
          "勝率": "0.500",
          "投球回": "16.3",
          "打者": "80",
          "被安打": "23",
          "被本塁打": "3",
          "奪三振": "13",
          "奪三振率": "6.88",
          "与四球": "7",
          "与死球": "2",
          "暴投": "0",
          "ボーク": "0",
          "失点": "14",
          "自責点": "14"
        },
        "三次": {
          "防御率": "2.65",
          "登板": "6",
          "完投": "0",
          "完封": "0",
          "無四球": "0",
          "勝利": "1",
          "敗戦": "1",
          "ホールド": "1",
          "HP": "1",
          "セーブ": "1",
          "勝率": "0.500",
          "投球回": "17",
          "打者": "71",
          "被安打": "16",
          "被本塁打": "1",
          "奪三振": "9",
          "奪三振率": "4.76",
          "与四球": "3",
          "与死球": "1",
          "暴投": "0",
          "ボーク": "0",
          "失点": "5",
          "自責点": "5"
        }
      },
      "被打数": "10223",
      "故意四球": "60",
      "QS率": "46.69",
      "BABIP": "0.299",
      "BB/9": "3.54",
      "HR/9": "1.04",
      "K%": "0.199",
      "BB%": "0.091"
    },
    "Pacific": {
      "id": "180513018",
      "防御率": "4.01",
      "登板": "1285",
      "先発": "300",
      "完投": "7",
      "完封": "4",
      "無四球": "2",
      "QS": "123",
      "交代完了": "293",
      "勝利": "145",
      "敗戦": "145",
      "ホールド": "250",
      "HP": "299",
      "セーブ": "81",
      "勝率": "0.500",
      "投球回": "2664.6",
      "打者": "11552",
      "被安打": "2521",
      "被本塁打": "314",
      "奪三振": "2177",
      "奪三振率": "7.35",
      "与四球": "1093",
      "与死球": "114",
      "暴投": "87",
      "ボーク": "9",
      "失点": "1312",
      "自責点": "1188",
      "被打率": "0.249",
      "K/BB": "1.99",
      "WHIP": "1.36",
      "対右": {
        "被打率": "0.247",
        "被打数": "5314",
        "被安打": "1314",
        "被本塁打": "231",
        "奪三振": "1194",
        "与四球": "568",
        "与死球": "79"
      },
      "対左": {
        "被打率": "0.252",
        "被打数": "4791",
        "被安打": "1207",
        "被本塁打": "83",
        "奪三振": "983",
        "与四球": "525",
        "与死球": "35"
      },
      "球場": {
        "東京ドーム": {
          "防御率": "3.68",
          "登板": "35",
          "完投": "0",
          "完封": "0",
          "無四球": "0",
          "勝利": "5",
          "敗戦": "5",
          "ホールド": "4",
          "HP": "6",
          "セーブ": "3",
          "勝率": "0.500",
          "投球回": "85.9",
          "打者": "373",
          "被安打": "83",
          "被本塁打": "8",
          "奪三振": "76",
          "奪三振率": "7.77",
          "与四球": "31",
          "与死球": "6",
          "暴投": "3",
          "ボーク": "0",
          "失点": "38",
          "自責点": "36"
        },
        "メットライフ": {
          "防御率": "4.95",
          "登板": "161",
          "完投": "2",
          "完封": "2",
          "無四球": "0",
          "勝利": "19",
          "敗戦": "19",
          "ホールド": "16",
          "HP": "20",
          "セーブ": "6",
          "勝率": "0.500",
          "投球回": "329.1",
          "打者": "1516",
          "被安打": "331",
          "被本塁打": "42",
          "奪三振": "233",
          "奪三振率": "6.37",
          "与四球": "188",
          "与死球": "15",
          "暴投": "13",
          "ボーク": "1",
          "失点": "207",
          "自責点": "181"
        },
        "京セラＤ大阪": {
          "防御率": "3.38",
          "登板": "189",
          "完投": "0",
          "完封": "0",
          "無四球": "0",
          "勝利": "20",
          "敗戦": "20",
          "ホールド": "42",
          "HP": "49",
          "セーブ": "12",
          "勝率": "0.500",
          "投球回": "393.3",
          "打者": "1687",
          "被安打": "354",
          "被本塁打": "31",
          "奪三振": "312",
          "奪三振率": "7.13",
          "与四球": "146",
          "与死球": "17",
          "暴投": "13",
          "ボーク": "2",
          "失点": "164",
          "自責点": "148"
        },
        "ヤフオクドーム": {
          "防御率": "3.95",
          "登板": "177",
          "完投": "0",
          "完封": "0",
          "無四球": "0",
          "勝利": "21",
          "敗戦": "21",
          "ホールド": "41",
          "HP": "48",
          "セーブ": "9",
          "勝率": "0.500",
          "投球回": "374.0",
          "打者": "1639",
          "被安打": "370",
          "被本塁打": "59",
          "奪三振": "316",
          "奪三振率": "7.60",
          "与四球": "145",
          "与死球": "14",
          "暴投": "10",
          "ボーク": "2",
          "失点": "177",
          "自責点": "164"
        },
        "盛岡": {
          "防御率": "4.24",
          "登板": "7",
          "完投": "0",
          "完封": "0",
          "無四球": "0",
          "勝利": "1",
          "敗戦": "1",
          "ホールド": "1",
          "HP": "1",
          "セーブ": "0",
          "勝率": "0.500",
          "投球回": "16.3",
          "打者": "67",
          "被安打": "11",
          "被本塁打": "4",
          "奪三振": "18",
          "奪三振率": "9.53",
          "与四球": "7",
          "与死球": "1",
          "暴投": "0",
          "ボーク": "0",
          "失点": "9",
          "自責点": "8"
        },
        "札幌ドーム": {
          "防御率": "3.94",
          "登板": "200",
          "完投": "2",
          "完封": "1",
          "無四球": "1",
          "勝利": "22",
          "敗戦": "22",
          "ホールド": "43",
          "HP": "49",
          "セーブ": "13",
          "勝率": "0.500",
          "投球回": "404.2",
          "打者": "1751",
          "被安打": "380",
          "被本塁打": "35",
          "奪三振": "347",
          "奪三振率": "7.72",
          "与四球": "157",
          "与死球": "11",
          "暴投": "11",
          "ボーク": "0",
          "失点": "190",
          "自責点": "177"
        },
        "北九州": {
          "防御率": "5.50",
          "登板": "11",
          "完投": "0",
          "完封": "0",
          "無四球": "0",
          "勝利": "1",
          "敗戦": "1",
          "ホールド": "0",
          "HP": "0",
          "セーブ": "1",
          "勝率": "0.500",
          "投球回": "15.9",
          "打者": "94",
          "被安打": "27",
          "被本塁打": "4",
          "奪三振": "16",
          "奪三振率": "8.00",
          "与四球": "12",
          "与死球": "2",
          "暴投": "1",
          "ボーク": "2",
          "失点": "18",
          "自責点": "11"
        },
        "前橋": {
          "防御率": "6.00",
          "登板": "7",
          "完投": "0",
          "完封": "0",
          "無四球": "0",
          "勝利": "1",
          "敗戦": "1",
          "ホールド": "0",
          "HP": "0",
          "セーブ": "0",
          "勝率": "0.500",
          "投球回": "18",
          "打者": "84",
          "被安打": "18",
          "被本塁打": "4",
          "奪三振": "14",
          "奪三振率": "7.00",
          "与四球": "8",
          "与死球": "3",
          "暴投": "0",
          "ボーク": "0",
          "失点": "13",
          "自責点": "12"
        },
        "那覇": {
          "防御率": "5.03",
          "登板": "16",
          "完投": "0",
          "完封": "0",
          "無四球": "0",
          "勝利": "2",
          "敗戦": "2",
          "ホールド": "1",
          "HP": "1",
          "セーブ": "1",
          "勝率": "0.500",
          "投球回": "31.9",
          "打者": "164",
          "被安打": "43",
          "被本塁打": "3",
          "奪三振": "37",
          "奪三振率": "9.79",
          "与四球": "18",
          "与死球": "1",
          "暴投": "1",
          "ボーク": "0",
          "失点": "23",
          "自責点": "19"
        },
        "ＺＯＺＯマリン": {
          "防御率": "3.83",
          "登板": "201",
          "完投": "2",
          "完封": "1",
          "無四球": "1",
          "勝利": "23",
          "敗戦": "23",
          "ホールド": "40",
          "HP": "49",
          "セーブ": "15",
          "勝率": "0.500",
          "投球回": "421.6",
          "打者": "1809",
          "被安打": "383",
          "被本塁打": "58",
          "奪三振": "341",
          "奪三振率": "7.26",
          "与四球": "149",
          "与死球": "23",
          "暴投": "17",
          "ボーク": "1",
          "失点": "199",
          "自責点": "180"
        },
        "弘前": {
          "防御率": "2.50",
          "登板": "9",
          "完投": "0",
          "完封": "0",
          "無四球": "0",
          "勝利": "1",
          "敗戦": "1",
          "ホールド": "3",
          "HP": "3",
          "セーブ": "1",
          "勝率": "0.500",
          "投球回": "17.3",
          "打者": "80",
          "被安打": "16",
          "被本塁打": "1",
          "奪三振": "14",
          "奪三振率": "7.00",
          "与四球": "10",
          "与死球": "1",
          "暴投": "0",
          "ボーク": "0",
          "失点": "5",
          "自責点": "5"
        },
        "県営大宮": {
          "防御率": "4.50",
          "登板": "21",
          "完投": "0",
          "完封": "0",
          "無四球": "0",
          "勝利": "2",
          "敗戦": "2",
          "ホールド": "6",
          "HP": "7",
          "セーブ": "2",
          "勝率": "0.500",
          "投球回": "38.6",
          "打者": "176",
          "被安打": "43",
          "被本塁打": "3",
          "奪三振": "29",
          "奪三振率": "6.53",
          "与四球": "18",
          "与死球": "1",
          "暴投": "1",
          "ボーク": "1",
          "失点": "22",
          "自責点": "20"
        },
        "楽天生命パーク": {
          "防御率": "4.29",
          "登板": "188",
          "完投": "1",
          "完封": "0",
          "無四球": "0",
          "勝利": "21",
          "敗戦": "21",
          "ホールド": "42",
          "HP": "53",
          "セーブ": "13",
          "勝率": "0.500",
          "投球回": "364.3",
          "打者": "1609",
          "被安打": "347",
          "被本塁打": "47",
          "奪三振": "322",
          "奪三振率": "7.94",
          "与四球": "157",
          "与死球": "17",
          "暴投": "12",
          "ボーク": "0",
          "失点": "186",
          "自責点": "174"
        },
        "ほっと神戸": {
          "防御率": "5.72",
          "登板": "41",
          "完投": "0",
          "完封": "0",
          "無四球": "0",
          "勝利": "4",
          "敗戦": "4",
          "ホールド": "6",
          "HP": "8",
          "セーブ": "3",
          "勝率": "0.500",
          "投球回": "67.2",
          "打者": "307",
          "被安打": "79",
          "被本塁打": "12",
          "奪三振": "60",
          "奪三振率": "7.98",
          "与四球": "24",
          "与死球": "0",
          "暴投": "3",
          "ボーク": "0",
          "失点": "46",
          "自責点": "43"
        },
        "熊本": {
          "防御率": "0.53",
          "登板": "5",
          "完投": "0",
          "完封": "0",
          "無四球": "0",
          "勝利": "1",
          "敗戦": "1",
          "ホールド": "1",
          "HP": "1",
          "セーブ": "1",
          "勝率": "0.500",
          "投球回": "17",
          "打者": "68",
          "被安打": "12",
          "被本塁打": "0",
          "奪三振": "18",
          "奪三振率": "9.53",
          "与四球": "8",
          "与死球": "0",
          "暴投": "1",
          "ボーク": "0",
          "失点": "3",
          "自責点": "1"
        },
        "長崎": {
          "防御率": "2.30",
          "登板": "12",
          "完投": "0",
          "完封": "0",
          "無四球": "0",
          "勝利": "0",
          "敗戦": "0",
          "ホールド": "4",
          "HP": "4",
          "セーブ": "0",
          "勝率": "0.000",
          "投球回": "14.5",
          "打者": "82",
          "被安打": "11",
          "被本塁打": "0",
          "奪三振": "20",
          "奪三振率": "11.49",
          "与四球": "12",
          "与死球": "2",
          "暴投": "1",
          "ボーク": "0",
          "失点": "6",
          "自責点": "4"
        },
        "鹿児島": {
          "防御率": "4.50",
          "登板": "5",
          "完投": "0",
          "完封": "0",
          "無四球": "0",
          "勝利": "1",
          "敗戦": "1",
          "ホールド": "0",
          "HP": "0",
          "セーブ": "1",
          "勝率": "0.500",
          "投球回": "10",
          "打者": "46",
          "被安打": "13",
          "被本塁打": "3",
          "奪三振": "4",
          "奪三振率": "3.60",
          "与四球": "3",
          "与死球": "0",
          "暴投": "0",
          "ボーク": "0",
          "失点": "6",
          "自責点": "5"
        }
      },
      "被打数": "10105",
      "故意四球": "34",
      "QS率": "41.00",
      "BABIP": "0.290",
      "BB/9": "3.69",
      "HR/9": "1.06",
      "K%": "0.188",
      "BB%": "0.095"
    }
  },
  "Hitter": {
    "Central": {
      "id": "155820001",
      "打率": "0.261",
      "試合": "3559",
      "打席": "11006",
      "打数": "9691",
      "安打": "2527",
      "二塁打": "438",
      "三塁打": "48",
      "本塁打": "310",
      "塁打": "3991",
      "打点": "1202",
      "得点": "1258",
      "三振": "2059",
      "四球": "1029",
      "死球": "89",
      "犠打": "139",
      "犠飛": "58",
      "盗塁": "155",
      "盗塁死": "68",
      "併殺打": "206",
      "出塁率": "0.335",
      "長打率": "0.412",
      "OPS": "0.747",
      "失策": "163",
      "対右": {
        "打率": "0.267",
        "打数": "6322",
        "安打": "1688",
        "本塁打": "189",
        "打点": "827",
        "三振": "1277",
        "四球": "674",
        "死球": "64",
        "犠打": "93",
        "犠飛": "38"
      },
      "対左": {
        "打率": "0.249",
        "打数": "3369",
        "安打": "839",
        "本塁打": "121",
        "打点": "375",
        "三振": "782",
        "四球": "355",
        "死球": "25",
        "犠打": "46",
        "犠飛": "20"
      },
      "カウント": {
        "0-0": {
          "打率": "0.344",
          "打数": "1068",
          "安打": "367",
          "本塁打": "62",
          "打点": "206",
          "三振": "0",
          "四球": "39",
          "死球": "31",
          "犠打": "64",
          "犠飛": "6"
        },
        "0-2": {
          "打率": "0.174",
          "打数": "743",
          "安打": "129",
          "本塁打": "3",
          "打点": "31",
          "三振": "340",
          "四球": "0",
          "死球": "8",
          "犠打": "2",
          "犠飛": "4"
        },
        "1-1": {
          "打率": "0.340",
          "打数": "966",
          "安打": "328",
          "本塁打": "49",
          "打点": "175",
          "三振": "0",
          "四球": "0",
          "死球": "8",
          "犠打": "18",
          "犠飛": "11"
        },
        "1-2": {
          "打率": "0.169",
          "打数": "1720",
          "安打": "290",
          "本塁打": "21",
          "打点": "97",
          "三振": "723",
          "四球": "0",
          "死球": "11",
          "犠打": "1",
          "犠飛": "7"
        },
        "2-2": {
          "打率": "0.196",
          "打数": "1634",
          "安打": "321",
          "本塁打": "29",
          "打点": "132",
          "三振": "638",
          "四球": "0",
          "死球": "3",
          "犠打": "3",
          "犠飛": "7"
        },
        "3-2": {
          "打率": "0.218",
          "打数": "1036",
          "安打": "226",
          "本塁打": "21",
          "打点": "94",
          "三振": "358",
          "四球": "497",
          "死球": "2",
          "犠打": "0",
          "犠飛": "2"
        },
        "0-1": {
          "打率": "0.333",
          "打数": "805",
          "安打": "268",
          "本塁打": "35",
          "打点": "123",
          "三振": "0",
          "四球": "0",
          "死球": "9",
          "犠打": "24",
          "犠飛": "4"
        },
        "1-0": {
          "打率": "0.371",
          "打数": "715",
          "安打": "265",
          "本塁打": "49",
          "打点": "158",
          "三振": "0",
          "四球": "3",
          "死球": "8",
          "犠打": "16",
          "犠飛": "9"
        },
        "2-0": {
          "打率": "0.339",
          "打数": "230",
          "安打": "78",
          "本塁打": "11",
          "打点": "50",
          "三振": "0",
          "四球": "9",
          "死球": "2",
          "犠打": "4",
          "犠飛": "1"
        },
        "2-1": {
          "打率": "0.337",
          "打数": "561",
          "安打": "189",
          "本塁打": "19",
          "打点": "84",
          "三振": "0",
          "四球": "1",
          "死球": "5",
          "犠打": "7",
          "犠飛": "4"
        },
        "3-0": {
          "打率": "0.524",
          "打数": "21",
          "安打": "11",
          "本塁打": "4",
          "打点": "13",
          "三振": "0",
          "四球": "164",
          "死球": "0",
          "犠打": "0",
          "犠飛": "0"
        },
        "3-1": {
          "打率": "0.286",
          "打数": "192",
          "安打": "55",
          "本塁打": "7",
          "打点": "39",
          "三振": "0",
          "四球": "316",
          "死球": "2",
          "犠打": "0",
          "犠飛": "3"
        }
      },
      "走者": {
        "無し": {
          "打率": "0.261",
          "打数": "5516",
          "安打": "1437",
          "本塁打": "188",
          "打点": "188",
          "三振": "1245",
          "四球": "510",
          "死球": "40",
          "犠打": "0",
          "犠飛": "0"
        },
        "一塁": {
          "打率": "0.274",
          "打数": "1736",
          "安打": "476",
          "本塁打": "58",
          "打点": "149",
          "三振": "308",
          "四球": "152",
          "死球": "21",
          "犠打": "105",
          "犠飛": "0"
        },
        "一二塁": {
          "打率": "0.250",
          "打数": "760",
          "安打": "190",
          "本塁打": "15",
          "打点": "188",
          "三振": "171",
          "四球": "75",
          "死球": "7",
          "犠打": "15",
          "犠飛": "0"
        },
        "二塁": {
          "打率": "0.226",
          "打数": "722",
          "安打": "163",
          "本塁打": "13",
          "打点": "114",
          "三振": "150",
          "四球": "139",
          "死球": "9",
          "犠打": "18",
          "犠飛": "0"
        },
        "満塁": {
          "打率": "0.288",
          "打数": "267",
          "安打": "77",
          "本塁打": "7",
          "打点": "218",
          "三振": "44",
          "四球": "23",
          "死球": "3",
          "犠打": "0",
          "犠飛": "21"
        },
        "一三塁": {
          "打率": "0.269",
          "打数": "279",
          "安打": "75",
          "本塁打": "17",
          "打点": "146",
          "三振": "50",
          "四球": "37",
          "死球": "1",
          "犠打": "1",
          "犠飛": "15"
        },
        "二三塁": {
          "打率": "0.279",
          "打数": "179",
          "安打": "50",
          "本塁打": "4",
          "打点": "110",
          "三振": "45",
          "四球": "48",
          "死球": "1",
          "犠打": "0",
          "犠飛": "9"
        },
        "三塁": {
          "打率": "0.254",
          "打数": "232",
          "安打": "59",
          "本塁打": "8",
          "打点": "89",
          "三振": "46",
          "四球": "45",
          "死球": "7",
          "犠打": "0",
          "犠飛": "13"
        }
      },
      "球場": {
        "東京ドーム": {
          "打率": "0.288",
          "試合": "540",
          "打数": "1434",
          "安打": "413",
          "本塁打": "73",
          "打点": "216",
          "三振": "310",
          "四球": "147",
          "死球": "17",
          "犠打": "19",
          "犠飛": "9",
          "盗塁": "27"
        },
        "ナゴヤドーム": {
          "打率": "0.256",
          "試合": "559",
          "打数": "1518",
          "安打": "388",
          "本塁打": "26",
          "打点": "162",
          "三振": "331",
          "四球": "135",
          "死球": "17",
          "犠打": "27",
          "犠飛": "9",
          "盗塁": "34"
        },
        "マツダスタジアム": {
          "打率": "0.257",
          "試合": "556",
          "打数": "1542",
          "安打": "397",
          "本塁打": "38",
          "打点": "181",
          "三振": "304",
          "四球": "178",
          "死球": "15",
          "犠打": "28",
          "犠飛": "14",
          "盗塁": "15"
        },
        "横浜": {
          "打率": "0.251",
          "試合": "485",
          "打数": "1305",
          "安打": "327",
          "本塁打": "46",
          "打点": "158",
          "三振": "274",
          "四球": "136",
          "死球": "10",
          "犠打": "12",
          "犠飛": "6",
          "盗塁": "17"
        },
        "神宮": {
          "打率": "0.260",
          "試合": "646",
          "打数": "1743",
          "安打": "454",
          "本塁打": "78",
          "打点": "245",
          "三振": "407",
          "四球": "193",
          "死球": "12",
          "犠打": "27",
          "犠飛": "13",
          "盗塁": "32"
        },
        "甲子園": {
          "打率": "0.263",
          "試合": "581",
          "打数": "1658",
          "安打": "436",
          "本塁打": "38",
          "打点": "184",
          "三振": "318",
          "四球": "184",
          "死球": "11",
          "犠打": "23",
          "犠飛": "3",
          "盗塁": "28"
        },
        "鹿児島": {
          "打率": "0.224",
          "試合": "23",
          "打数": "58",
          "安打": "13",
          "本塁打": "3",
          "打点": "9",
          "三振": "18",
          "四球": "9",
          "死球": "1",
          "犠打": "0",
          "犠飛": "2",
          "盗塁": "0"
        },
        "熊本": {
          "打率": "0.250",
          "試合": "26",
          "打数": "60",
          "安打": "15",
          "本塁打": "2",
          "打点": "9",
          "三振": "15",
          "四球": "9",
          "死球": "2",
          "犠打": "1",
          "犠飛": "0",
          "盗塁": "0"
        },
        "新潟": {
          "打率": "0.279",
          "試合": "27",
          "打数": "68",
          "安打": "19",
          "本塁打": "1",
          "打点": "13",
          "三振": "12",
          "四球": "8",
          "死球": "0",
          "犠打": "1",
          "犠飛": "0",
          "盗塁": "1"
        },
        "京セラＤ大阪": {
          "打率": "0.159",
          "試合": "66",
          "打数": "176",
          "安打": "28",
          "本塁打": "1",
          "打点": "6",
          "三振": "50",
          "四球": "20",
          "死球": "1",
          "犠打": "1",
          "犠飛": "2",
          "盗塁": "1"
        },
        "松山": {
          "打率": "0.333",
          "試合": "23",
          "打数": "66",
          "安打": "22",
          "本塁打": "3",
          "打点": "14",
          "三振": "11",
          "四球": "7",
          "死球": "2",
          "犠打": "0",
          "犠飛": "0",
          "盗塁": "0"
        },
        "三次": {
          "打率": "0.238",
          "試合": "27",
          "打数": "63",
          "安打": "15",
          "本塁打": "1",
          "打点": "5",
          "三振": "9",
          "四球": "3",
          "死球": "1",
          "犠打": "0",
          "犠飛": "0",
          "盗塁": "0"
        }
      },
      "故意四球": "59",
      "得点圏打率": "0.252",
      "得点圏打席": "2926",
      "得点圏打数": "2439",
      "得点圏安打": "614",
      "得点圏本塁打": "64",
      "得点圏打点": "865",
      "得点圏三振": "506",
      "得点圏四球": "367",
      "得点圏死球": "28",
      "得点圏犠打": "34",
      "得点圏犠飛": "58",
      "wOBA": "0.328",
      "wOBA(Basic)": "0.329",
      "wOBA(Speed)": "0.328",
      "RC": "1353.21",
      "RC27": "4.79",
      "XR": "1347.70",
      "XR27": "4.77",
      "IsoP": "0.151",
      "BB/K": "0.50",
      "BB%": "0.093",
      "K%": "0.187",
      "IsoD": "0.074",
      "BABIP": "0.300"
    },
    "Pacific": {
      "id": "165228039",
      "打率": "0.249",
      "試合": "3512",
      "打席": "11552",
      "打数": "10105",
      "安打": "2521",
      "二塁打": "446",
      "三塁打": "45",
      "本塁打": "314",
      "塁打": "3999",
      "打点": "1254",
      "得点": "1312",
      "三振": "2177",
      "四球": "1093",
      "死球": "114",
      "犠打": "176",
      "犠飛": "64",
      "盗塁": "227",
      "盗塁死": "92",
      "併殺打": "193",
      "出塁率": "0.328",
      "長打率": "0.396",
      "OPS": "0.723",
      "失策": "150",
      "得点圏打率": "0.263",
      "得点圏打席": "3020",
      "得点圏打数": "2489",
      "得点圏安打": "654",
      "得点圏本塁打": "72",
      "得点圏打点": "920",
      "得点圏三振": "532",
      "得点圏四球": "381",
      "得点圏死球": "31",
      "得点圏犠打": "55",
      "得点圏犠飛": "64",
      "対右": {
        "打率": "0.251",
        "打数": "7816",
        "安打": "1961",
        "本塁打": "247",
        "打点": "979",
        "三振": "1707",
        "四球": "853",
        "死球": "88",
        "犠打": "135",
        "犠飛": "51"
      },
      "カウント": {
        "0-2": {
          "打率": "0.132",
          "打数": "796",
          "安打": "105",
          "本塁打": "8",
          "打点": "39",
          "三振": "383",
          "四球": "0",
          "死球": "7",
          "犠打": "1",
          "犠飛": "3"
        },
        "1-0": {
          "打率": "0.348",
          "打数": "727",
          "安打": "253",
          "本塁打": "38",
          "打点": "145",
          "三振": "0",
          "四球": "2",
          "死球": "13",
          "犠打": "27",
          "犠飛": "8"
        },
        "1-2": {
          "打率": "0.171",
          "打数": "1800",
          "安打": "307",
          "本塁打": "26",
          "打点": "119",
          "三振": "755",
          "四球": "0",
          "死球": "11",
          "犠打": "0",
          "犠飛": "6"
        },
        "2-1": {
          "打率": "0.311",
          "打数": "637",
          "安打": "198",
          "本塁打": "27",
          "打点": "89",
          "三振": "0",
          "四球": "1",
          "死球": "4",
          "犠打": "6",
          "犠飛": "7"
        },
        "2-2": {
          "打率": "0.188",
          "打数": "1729",
          "安打": "325",
          "本塁打": "32",
          "打点": "138",
          "三振": "658",
          "四球": "0",
          "死球": "11",
          "犠打": "0",
          "犠飛": "4"
        },
        "3-1": {
          "打率": "0.390",
          "打数": "223",
          "安打": "87",
          "本塁打": "16",
          "打点": "62",
          "三振": "0",
          "四球": "303",
          "死球": "3",
          "犠打": "3",
          "犠飛": "2"
        },
        "3-2": {
          "打率": "0.220",
          "打数": "1097",
          "安打": "241",
          "本塁打": "29",
          "打点": "136",
          "三振": "381",
          "四球": "568",
          "死球": "9",
          "犠打": "0",
          "犠飛": "7"
        },
        "0-0": {
          "打率": "0.320",
          "打数": "1142",
          "安打": "366",
          "本塁打": "54",
          "打点": "210",
          "三振": "0",
          "四球": "24",
          "死球": "27",
          "犠打": "87",
          "犠飛": "14"
        },
        "0-1": {
          "打率": "0.300",
          "打数": "774",
          "安打": "232",
          "本塁打": "24",
          "打点": "95",
          "三振": "0",
          "四球": "0",
          "死球": "14",
          "犠打": "31",
          "犠飛": "2"
        },
        "1-1": {
          "打率": "0.333",
          "打数": "943",
          "安打": "314",
          "本塁打": "39",
          "打点": "143",
          "三振": "0",
          "四球": "0",
          "死球": "12",
          "犠打": "17",
          "犠飛": "7"
        },
        "2-0": {
          "打率": "0.392",
          "打数": "217",
          "安打": "85",
          "本塁打": "21",
          "打点": "63",
          "三振": "0",
          "四球": "2",
          "死球": "3",
          "犠打": "3",
          "犠飛": "3"
        },
        "3-0": {
          "打率": "0.400",
          "打数": "20",
          "安打": "8",
          "本塁打": "0",
          "打点": "15",
          "三振": "0",
          "四球": "193",
          "死球": "0",
          "犠打": "1",
          "犠飛": "1"
        }
      },
      "走者": {
        "無し": {
          "打率": "0.240",
          "打数": "5879",
          "安打": "1410",
          "本塁打": "187",
          "打点": "187",
          "三振": "1285",
          "四球": "546",
          "死球": "63",
          "犠打": "0",
          "犠飛": "0"
        },
        "一塁": {
          "打率": "0.263",
          "打数": "1737",
          "安打": "457",
          "本塁打": "55",
          "打点": "147",
          "三振": "360",
          "四球": "166",
          "死球": "20",
          "犠打": "121",
          "犠飛": "0"
        },
        "満塁": {
          "打率": "0.286",
          "打数": "283",
          "安打": "81",
          "本塁打": "9",
          "打点": "218",
          "三振": "70",
          "四球": "26",
          "死球": "1",
          "犠打": "0",
          "犠飛": "14"
        },
        "一二塁": {
          "打率": "0.239",
          "打数": "721",
          "安打": "172",
          "本塁打": "20",
          "打点": "176",
          "三振": "142",
          "四球": "81",
          "死球": "10",
          "犠打": "29",
          "犠飛": "0"
        },
        "一三塁": {
          "打率": "0.282",
          "打数": "248",
          "安打": "70",
          "本塁打": "4",
          "打点": "128",
          "三振": "45",
          "四球": "37",
          "死球": "2",
          "犠打": "4",
          "犠飛": "20"
        },
        "二塁": {
          "打率": "0.250",
          "打数": "787",
          "安打": "197",
          "本塁打": "20",
          "打点": "150",
          "三振": "179",
          "四球": "158",
          "死球": "16",
          "犠打": "20",
          "犠飛": "0"
        },
        "二三塁": {
          "打率": "0.254",
          "打数": "209",
          "安打": "53",
          "本塁打": "9",
          "打点": "131",
          "三振": "49",
          "四球": "29",
          "死球": "1",
          "犠打": "0",
          "犠飛": "15"
        },
        "三塁": {
          "打率": "0.336",
          "打数": "241",
          "安打": "81",
          "本塁打": "10",
          "打点": "117",
          "三振": "47",
          "四球": "50",
          "死球": "1",
          "犠打": "2",
          "犠飛": "15"
        }
      },
      "球場": {
        "東京ドーム": {
          "打率": "0.249",
          "試合": "115",
          "打数": "333",
          "安打": "83",
          "本塁打": "8",
          "打点": "38",
          "三振": "76",
          "四球": "31",
          "死球": "6",
          "犠打": "3",
          "犠飛": "0",
          "盗塁": "5"
        },
        "メットライフ": {
          "打率": "0.259",
          "試合": "432",
          "打数": "1280",
          "安打": "331",
          "本塁打": "42",
          "打点": "195",
          "三振": "233",
          "四球": "188",
          "死球": "15",
          "犠打": "20",
          "犠飛": "13",
          "盗塁": "38"
        },
        "ＺＯＺＯマリン": {
          "打率": "0.239",
          "試合": "560",
          "打数": "1603",
          "安打": "383",
          "本塁打": "58",
          "打点": "193",
          "三振": "341",
          "四球": "149",
          "死球": "23",
          "犠打": "29",
          "犠飛": "5",
          "盗塁": "39"
        },
        "ヤフオクドーム": {
          "打率": "0.255",
          "試合": "484",
          "打数": "1451",
          "安打": "370",
          "本塁打": "59",
          "打点": "173",
          "三振": "316",
          "四球": "145",
          "死球": "14",
          "犠打": "22",
          "犠飛": "7",
          "盗塁": "27"
        },
        "県営大宮": {
          "打率": "0.281",
          "試合": "48",
          "打数": "153",
          "安打": "43",
          "本塁打": "3",
          "打点": "21",
          "三振": "29",
          "四球": "18",
          "死球": "1",
          "犠打": "4",
          "犠飛": "0",
          "盗塁": "4"
        },
        "札幌ドーム": {
          "打率": "0.245",
          "試合": "548",
          "打数": "1550",
          "安打": "380",
          "本塁打": "35",
          "打点": "180",
          "三振": "347",
          "四球": "157",
          "死球": "11",
          "犠打": "27",
          "犠飛": "6",
          "盗塁": "33"
        },
        "楽天生命パーク": {
          "打率": "0.247",
          "試合": "482",
          "打数": "1403",
          "安打": "347",
          "本塁打": "47",
          "打点": "182",
          "三振": "322",
          "四球": "157",
          "死球": "17",
          "犠打": "23",
          "犠飛": "9",
          "盗塁": "17"
        },
        "京セラＤ大阪": {
          "打率": "0.239",
          "試合": "540",
          "打数": "1480",
          "安打": "354",
          "本塁打": "31",
          "打点": "157",
          "三振": "312",
          "四球": "146",
          "死球": "17",
          "犠打": "30",
          "犠飛": "14",
          "盗塁": "41"
        },
        "弘前": {
          "打率": "0.239",
          "試合": "21",
          "打数": "67",
          "安打": "16",
          "本塁打": "1",
          "打点": "5",
          "三振": "14",
          "四球": "10",
          "死球": "1",
          "犠打": "1",
          "犠飛": "1",
          "盗塁": "2"
        },
        "北九州": {
          "打率": "0.346",
          "試合": "23",
          "打数": "78",
          "安打": "27",
          "本塁打": "4",
          "打点": "14",
          "三振": "16",
          "四球": "12",
          "死球": "2",
          "犠打": "1",
          "犠飛": "1",
          "盗塁": "4"
        },
        "前橋": {
          "打率": "0.250",
          "試合": "25",
          "打数": "72",
          "安打": "18",
          "本塁打": "4",
          "打点": "13",
          "三振": "14",
          "四球": "8",
          "死球": "3",
          "犠打": "1",
          "犠飛": "0",
          "盗塁": "2"
        },
        "盛岡": {
          "打率": "0.186",
          "試合": "22",
          "打数": "59",
          "安打": "11",
          "本塁打": "4",
          "打点": "7",
          "三振": "18",
          "四球": "7",
          "死球": "1",
          "犠打": "0",
          "犠飛": "0",
          "盗塁": "2"
        },
        "那覇": {
          "打率": "0.307",
          "試合": "47",
          "打数": "140",
          "安打": "43",
          "本塁打": "3",
          "打点": "20",
          "三振": "37",
          "四球": "18",
          "死球": "1",
          "犠打": "3",
          "犠飛": "2",
          "盗塁": "5"
        },
        "ほっと神戸": {
          "打率": "0.287",
          "試合": "96",
          "打数": "275",
          "安打": "79",
          "本塁打": "12",
          "打点": "43",
          "三振": "60",
          "四球": "24",
          "死球": "0",
          "犠打": "5",
          "犠飛": "3",
          "盗塁": "5"
        },
        "熊本": {
          "打率": "0.214",
          "試合": "24",
          "打数": "56",
          "安打": "12",
          "本塁打": "0",
          "打点": "2",
          "三振": "18",
          "四球": "8",
          "死球": "0",
          "犠打": "3",
          "犠飛": "1",
          "盗塁": "1"
        },
        "鹿児島": {
          "打率": "0.310",
          "試合": "20",
          "打数": "42",
          "安打": "13",
          "本塁打": "3",
          "打点": "5",
          "三振": "4",
          "四球": "3",
          "死球": "0",
          "犠打": "1",
          "犠飛": "0",
          "盗塁": "0"
        },
        "長崎": {
          "打率": "0.175",
          "試合": "25",
          "打数": "63",
          "安打": "11",
          "本塁打": "0",
          "打点": "6",
          "三振": "20",
          "四球": "12",
          "死球": "2",
          "犠打": "3",
          "犠飛": "2",
          "盗塁": "2"
        }
      },
      "故意四球": "33",
      "対左": {
        "打率": "0.245",
        "打数": "2289",
        "安打": "560",
        "本塁打": "67",
        "打点": "275",
        "三振": "470",
        "四球": "240",
        "死球": "26",
        "犠打": "41",
        "犠飛": "13"
      },
      "wOBA": "0.319",
      "wOBA(Basic)": "0.320",
      "wOBA(Speed)": "0.320",
      "RC": "1347.48",
      "RC27": "4.49",
      "XR": "1356.24",
      "XR27": "4.52",
      "IsoP": "0.146",
      "BB/K": "0.50",
      "BB%": "0.095",
      "K%": "0.188",
      "IsoD": "0.079",
      "BABIP": "0.287"
    }
  }
}