{
  "Pitcher": [
    {
      "Name": "山口 俊",
      "Team": "読売ジャイアンツ",
      "League": "Central",
      "防御率": "1.98",
      "登板": "6",
      "先発": "6",
      "完投": "0",
      "完封": "0",
      "無四球": "0",
      "QS": "5",
      "交代完了": "0",
      "勝利": "4",
      "敗戦": "0",
      "ホールド": "0",
      "HP": "0",
      "セーブ": "0",
      "勝率": "1.000",
      "投球回": "41",
      "打者": "165",
      "被安打": "26",
      "被本塁打": "2",
      "奪三振": "37",
      "奪三振率": "8.12",
      "与四球": "20",
      "与死球": "4",
      "暴投": "1",
      "ボーク": "0",
      "失点": "10",
      "自責点": "9",
      "被打率": ".190",
      "K/BB": "1.85",
      "WHIP": "1.12",
      "対右": {
        "被打率": ".148",
        "被打数": "61",
        "被安打": "9",
        "被本塁打": "2",
        "奪三振": "17",
        "与四球": "12",
        "与死球": "4"
      },
      "対左": {
        "被打率": ".224",
        "被打数": "76",
        "被安打": "17",
        "被本塁打": "0",
        "奪三振": "20",
        "与四球": "8",
        "与死球": "0"
      },
      "被打数": "137",
      "故意四球": "0",
      "QS率": "83.33",
      "BB/9": "4.39",
      "HR/9": "0.44",
      "FIP": 