{
  "Pitcher": {
    "Central": {
      "防御率": "3.64",
      "登板": "3246",
      "先発": "766",
      "完投": "24",
      "完封": "11",
      "QS": "387",
      "勝利": "346",
      "敗戦": "335",
      "ホールド": "580",
      "HP": "676",
      "セーブ": "180",
      "勝率": "0.508",
      "投球回": "6665.9",
      "被安打": "6340",
      "被本塁打": "686",
      "奪三振": "5554",
      "奪三振率": "7.50",
      "与四球": "2244",
      "与死球": "237",
      "暴投": "180",
      "ボーク": "13",
      "失点": "2928",
      "自責点": "2698",
      "被打率": "0.248",
      "K/BB": "2.48",
      "WHIP": "1.29",
      "アウト": "20102.0",
      "故意四球": "119",
      "打者": "28004",
      "被打数": "25523",
      "QS率": "50.5",
      "BABIP": ".293",
      "BB/9": "3.03",
      "HR/9": "0.93",
      "K%": "19.8",
      "BB%": "8.0",
      "HR%": "2.45",
      "K-BB%": "11.8",
      "LOB%": "75.0",
      "小松式ドネーション": "31162000",
      "ONE OUTS(万)": "-4589000"
    },
    "Pacific": {
      "防御率": "3.55",
      "登板": "3185",
      "先発": "761",
      "完投": "20",
      "完封": "11",
      "QS": "362",
      "勝利": "331",
      "敗戦": "332",
      "ホールド": "552",
      "HP": "636",
      "セーブ": "187",
      "勝率": "0.499",
      "投球回": "6660.8",
      "被安打": "6012",
      "被本塁打": "630",
      "奪三振": "5637",
      "奪三振率": "7.61",
      "与四球": "2445",
      "与死球": "275",
      "暴投": "205",
      "ボーク": "14",
      "失点": "2846",
      "自責点": "2628",
      "被打率": "0.239",
      "K/BB": "2.31",
      "WHIP": "1.27",
      "アウト": "20086.0",
      "故意四球": "74",
      "打者": "27893",
      "被打数": "25173",
      "QS率": "47.6",
      "BABIP": ".285",
      "BB/9": "3.30",
      "HR/9": "0.85",
      "K%": "20.2",
      "BB%": "8.8",
      "HR%": "2.26",
      "K-BB%": "11.4",
      "LOB%": "75.0",
      "小松式ドネーション": "30786000",
      "ONE OUTS(万)": "-4187000"
    }
  },
  "Hitter": {
    "Central": {
      "打率": "0.259",
      "試合": "9636",
      "打席": "26650",
      "打数": "23847",
      "安打": "6178",
      "二塁打": "1113",
      "三塁打": "90",
      "本塁打": "681",
      "塁打": "9514",
      "打点": "2734",
      "得点": "2858",
      "三振": "4928",
      "四球": "2165",
      "死球": "223",
      "犠打": "268",
      "犠飛": "147",
      "盗塁": "378",
      "盗塁死": "180",
      "併殺打": "516",
      "出塁率": "0.325",
      "長打率": "0.399",
      "OPS": "0.724",
      "失策": "310",
      "故意四球": "0",
      "本塁打率": ".0286",
      "盗成功率": "67.7",
      "wOBA": ".319",
      "RC": "3087.56",
      "RC27": "4.44",
      "XR": "3089.52",
      "XR27": "4.44",
      "IsoP": ".140",
      "BB/K": "0.44",
      "BB%": "8.1",
      "K%": "18.5",
      "IsoD": ".066",
      "BABIP": ".299",
      "アダムダン率": "29.2",
      "ONE OUTS(万)": "-16935000"
    },
    "Pacific": {
      "打率": "0.244",
      "試合": "9300",
      "打席": "27642",
      "打数": "24225",
      "安打": "5907",
      "二塁打": "1053",
      "三塁打": "117",
      "本塁打": "582",
      "塁打": "8940",
      "打点": "2685",
      "得点": "2825",
      "三振": "5389",
      "四球": "2454",
      "死球": "277",
      "犠打": "482",
      "犠飛": "204",
      "盗塁": "417",
      "盗塁死": "184",
      "併殺打": "480",
      "出塁率": "0.318",
      "長打率": "0.369",
      "OPS": "0.687",
      "失策": "315",
      "故意四球": "0",
      "本塁打率": ".0240",
      "盗成功率": "69.4",
      "wOBA": ".306",
      "RC": "2916.50",
      "RC27": "4.00",
      "XR": "2965.57",
      "XR27": "4.07",
      "IsoP": ".125",
      "BB/K": "0.46",
      "BB%": "8.9",
      "K%": "19.5",
      "IsoD": ".074",
      "BABIP": ".288",
      "アダムダン率": "30.5",
      "ONE OUTS(万)": "-18210000"
    }
  }
}