{
  "Team": [
    {
      "チーム": "阪神",
      "League": "Central",
      "試合": "113",
      "勝利": "62",
      "敗戦": "46",
      "引分": "5",
      "勝率": ".574",
      "勝差": "0",
      "残試合": "30",
      "得点": "452",
      "失点": "434",
      "本塁打": "105",
      "盗塁": "95",
      "打率": ".252",
      "防御率": "3.55",
      "登板": "436",
      "先発": "113",
      "完投": "4",
      "完封": "0",
      "QS": "64",
      "ホールド": "70",
      "HP": "85",
      "セーブ": "33",
      "投球回": "985.4",
      "被安打": "929",
      "被本塁打": "92",
      "奪三振": "764",
      "奪三振率": "6.97",
      "与四球": "321",
      "与死球": "25",
      "暴投": "31",
      "ボーク": "1",
      "自責点": "391",
      "被打率": "0.244",
      "K/BB": "2.38",
      "WHIP": "1.27",
      "アウト": "2973.0",
      "故意四球": "26",
      "打者": "4153",
      "被打数": "3807",
      "打席": "3922",
      "打数": "3524",
      "安打": "913",
      "二塁打": "165",
      "三塁打": "21",
      "塁打": "1432",
      "打点": "428",
      "三振": "762",
      "四球": "313",
      "死球": "31",
      "犠打": "27",
      "犠飛": "27",
      "盗塁死": "24",
      "併殺打": "75",
      "出塁率": "0.323",
      "長打率": "0.406",
      "OPS": "0.729",
      "失策": "66"
    },
    {
      "チーム": "ヤクルト",
      "League": "Central",
      "試合": "109",
      "勝利": "53",
      "敗戦": "42",
      "引分": "14",
      "勝率": ".558",
      "勝差": "2.5",
      "残試合": "34",
      "得点": "486",
      "失点": "419",
      "本塁打": "110",
      "盗塁": "65",
      "打率": ".258",
      "防御率": "3.62",
      "登板": "482",
      "先発": "109",
      "完投": "3",
      "完封": "1",
      "QS": "47",
      "ホールド": "108",
      "HP": "125",
      "セーブ": "31",
      "投球回": "951.1",
      "被安打": "933",
      "被本塁打": "124",
      "奪三振": "867",
      "奪三振率": "8.20",
      "与四球": "284",
      "与死球": "38",
      "暴投": "26",
      "ボーク": "3",
      "自責点": "385",
      "被打率": "0.262",
      "K/BB": "3.05",
      "WHIP": "1.28",
      "アウト": "2875.0",
      "故意四球": "16",
      "打者": "3883",
      "被打数": "3561",
      "打席": "3913",
      "打数": "3414",
      "安打": "908",
      "二塁打": "168",
      "三塁打": "15",
      "塁打": "1433",
      "打点": "459",
      "三振": "726",
      "四球": "386",
      "死球": "46",
      "犠打": "47",
      "犠飛": "20",
      "盗塁死": "21",
      "併殺打": "78",
      "出塁率": "0.347",
      "長打率": "0.420",
      "OPS": "0.766",
      "失策": "46"
    },
    {
      "チーム": "巨人",
      "League": "Central",
      "試合": "115",
      "勝利": "54",
      "敗戦": "45",
      "引分": "16",
      "勝率": ".545",
      "勝差": "1",
      "残試合": "28",
      "得点": "459",
      "失点": "446",
      "本塁打": "144",
      "盗塁": "60",
      "打率": ".246",
      "防御率": "3.66",
      "登板": "515",
      "先発": "105",
      "完投": "4",
      "完封": "2",
      "QS": "49",
      "ホールド": "96",
      "HP": "110",
      "セーブ": "30",
      "投球回": "953.8",
      "被安打": "881",
      "被本塁打": "117",
      "奪三振": "820",
      "奪三振率": "7.72",
      "与四球": "354",
      "与死球": "48",
      "暴投": "22",
      "ボーク": "3",
      "自責点": "398",
      "被打率": "0.243",
      "K/BB": "2.32",
      "WHIP": "1.29",
      "アウト": "2874.0",
      "故意四球": "15",
      "打者": "4030",
      "被打数": "3628",
      "打席": "3807",
      "打数": "3416",
      "安打": "876",
      "二塁打": "166",
      "三塁打": "10",
      "塁打": "1470",
      "打点": "417",
      "三振": "747",
      "四球": "323",
      "死球": "32",
      "犠打": "17",
      "犠飛": "19",
      "盗塁死": "32",
      "併殺打": "74",
      "出塁率": "0.325",
      "長打率": "0.430",
      "OPS": "0.755",
      "失策": "29"
    },
    {
      "チーム": "中日",
      "League": "Central",
      "試合": "115",
      "勝利": "46",
      "敗戦": "55",
      "引分": "14",
      "勝率": ".455",
      "勝差": "9",
      "残試合": "28",
      "得点": "350",
      "失点": "374",
      "本塁打": "63",
      "盗塁": "54",
      "打率": ".241",
      "防御率": "3.14",
      "登板": "439",
      "先発": "115",
      "完投": "4",
      "完封": "2",
      "QS": "60",
      "ホールド": "83",
      "HP": "95",
      "セーブ": "13",
      "投球回": "961.1",
      "被安打": "897",
      "被本塁打": "76",
      "奪三振": "762",
      "奪三振率": "7.13",
      "与四球": "282",
      "与死球": "27",
      "暴投": "23",
      "ボーク": "1",
      "自責点": "342",
      "被打率": "0.244",
      "K/BB": "2.70",
      "WHIP": "1.23",
      "アウト": "2898.0",
      "故意四球": "14",
      "打者": "3982",
      "被打数": "3673",
      "打席": "3861",
      "打数": "3487",
      "安打": "870",
      "二塁打": "151",
      "三塁打": "19",
      "塁打": "1248",
      "打点": "322",
      "三振": "673",
      "四球": "274",
      "死球": "26",
      "犠打": "55",
      "犠飛": "19",
      "盗塁死": "31",
      "併殺打": "82",
      "出塁率": "0.307",
      "長打率": "0.358",
      "OPS": "0.665",
      "失策": "41"
    },
    {
      "チーム": "ＤｅＮＡ",
      "League": "Central",
      "試合": "113",
      "勝利": "44",
      "敗戦": "55",
      "引分": "14",
      "勝率": ".444",
      "勝差": "1",
      "残試合": "30",
      "得点": "454",
      "失点": "507",
      "本塁打": "116",
      "盗塁": "24",
      "打率": ".257",
      "防御率": "4.28",
      "登板": "503",
      "先発": "113",
      "完投": "1",
      "完封": "1",
      "QS": "42",
      "ホールド": "86",
      "HP": "101",
      "セーブ": "23",
      "投球回": "949.0",
      "被安打": "954",
      "被本塁打": "98",
      "奪三振": "796",
      "奪三振率": "7.55",
      "与四球": "370",
      "与死球": "36",
      "暴投": "34",
      "ボーク": "2",
      "自責点": "446",
      "被打率": "0.261",
      "K/BB": "2.15",
      "WHIP": "1.40",
      "アウト": "2861.0",
      "故意四球": "14",
      "打者": "4066",
      "被打数": "3660",
      "打席": "3673",
      "打数": "3298",
      "安打": "879",
      "二塁打": "176",
      "三塁打": "10",
      "塁打": "1363",
      "打点": "385",
      "三振": "657",
      "四球": "279",
      "死球": "31",
      "犠打": "49",
      "犠飛": "16",
      "盗塁死": "13",
      "併殺打": "69",
      "出塁率": "0.328",
      "長打率": "0.413",
      "OPS": "0.741",
      "失策": "44"
    },
    {
      "チーム": "広島",
      "League": "Central",
      "試合": "111",
      "勝利": "43",
      "敗戦": "58",
      "引分": "10",
      "勝率": ".426",
      "勝差": "2",
      "残試合": "32",
      "得点": "416",
      "失点": "469",
      "本塁打": "94",
      "盗塁": "51",
      "打率": ".259",
      "防御率": "3.92",
      "登板": "460",
      "先発": "110",
      "完投": "3",
      "完封": "1",
      "QS": "60",
      "ホールド": "65",
      "HP": "77",
      "セーブ": "24",
      "投球回": "958.8",
      "被安打": "949",
      "被本塁打": "101",
      "奪三振": "771",
      "奪三振率": "7.22",
      "与四球": "372",
      "与死球": "35",
      "暴投": "27",
      "ボーク": "3",
      "自責点": "420",
      "被打率": "0.254",
      "K/BB": "2.07",
      "WHIP": "1.38",
      "アウト": "2896.0",
      "故意四球": "17",
      "打者": "4138",
      "被打数": "3731",
      "打席": "3921",
      "打数": "3513",
      "安打": "939",
      "二塁打": "147",
      "三塁打": "10",
      "塁打": "1388",
      "打点": "389",
      "三振": "683",
      "四球": "320",
      "死球": "28",
      "犠打": "35",
      "犠飛": "25",
      "盗塁死": "32",
      "併殺打": "67",
      "出塁率": "0.331",
      "長打率": "0.395",
      "OPS": "0.726",
      "失策": "50"
    },
    {
      "チーム": "ロッテ",
      "League": "Pacific",
      "試合": "112",
      "勝利": "54",
      "敗戦": "41",
      "引分": "17",
      "勝率": ".568",
      "勝差": "0",
      "残試合": "31",
      "得点": "496",
      "失点": "444",
      "本塁打": "104",
      "盗塁": "97",
      "打率": ".249",
      "防御率": "3.74",
      "登板": "455",
      "先発": "112",
      "完投": "2",
      "完封": "0",
      "QS": "49",
      "ホールド": "86",
      "HP": "104",
      "セーブ": "34",
      "投球回": "971.1",
      "被安打": "924",
      "被本塁打": "116",
      "奪三振": "752",
      "奪三振率": "6.97",
      "与四球": "330",
      "与死球": "27",
      "暴投": "37",
      "ボーク": "2",
      "自責点": "410",
      "被打率": "0.240",
      "K/BB": "2.28",
      "WHIP": "1.29",
      "アウト": "2928.0",
      "故意四球": "15",
      "打者": "4199",
      "被打数": "3842",
      "打席": "4098",
      "打数": "3530",
      "安打": "889",
      "二塁打": "190",
      "三塁打": "11",
      "塁打": "1407",
      "打点": "467",
      "三振": "814",
      "四球": "417",
      "死球": "42",
      "犠打": "69",
      "犠飛": "40",
      "盗塁死": "27",
      "併殺打": "72",
      "出塁率": "0.335",
      "長打率": "0.399",
      "OPS": "0.733",
      "失策": "42"
    },
    {
      "チーム": "オリックス",
      "League": "Pacific",
      "試合": "115",
      "勝利": "54",
      "敗戦": "46",
      "引分": "15",
      "勝率": ".540",
      "勝差": "2.5",
      "残試合": "28",
      "得点": "445",
      "失点": "429",
      "本塁打": "105",
      "盗塁": "35",
      "打率": ".250",
      "防御率": "3.55",
      "登板": "451",
      "先発": "114",
      "完投": "4",
      "完封": "2",
      "QS": "63",
      "ホールド": "74",
      "HP": "87",
      "セーブ": "27",
      "投球回": "988.3",
      "被安打": "875",
      "被本塁打": "88",
      "奪三振": "847",
      "奪三振率": "7.71",
      "与四球": "332",
      "与死球": "40",
      "暴投": "19",
      "ボーク": "2",
      "自責点": "381",
      "被打率": "0.241",
      "K/BB": "2.55",
      "WHIP": "1.22",
      "アウト": "2981.0",
      "故意四球": "10",
      "打者": "4007",
      "被打数": "3635",
      "打席": "3722",
      "打数": "3320",
      "安打": "818",
      "二塁打": "131",
      "三塁打": "11",
      "塁打": "1196",
      "打点": "342",
      "三振": "646",
      "四球": "272",
      "死球": "49",
      "犠打": "60",
      "犠飛": "21",
      "盗塁死": "19",
      "併殺打": "76",
      "出塁率": "0.311",
      "長打率": "0.360",
      "OPS": "0.671",
      "失策": "57"
    },
    {
      "チーム": "楽天",
      "League": "Pacific",
      "試合": "114",
      "勝利": "52",
      "敗戦": "49",
      "引分": "13",
      "勝率": ".515",
      "勝差": "2.5",
      "残試合": "29",
      "得点": "435",
      "失点": "420",
      "本塁打": "89",
      "盗塁": "41",
      "打率": ".246",
      "防御率": "3.54",
      "登板": "454",
      "先発": "114",
      "完投": "4",
      "完封": "3",
      "QS": "56",
      "ホールド": "78",
      "HP": "89",
      "セーブ": "28",
      "投球回": "994.9",
      "被安打": "922",
      "被本塁打": "93",
      "奪三振": "894",
      "奪三振率": "8.07",
      "与四球": "305",
      "与死球": "28",
      "暴投": "21",
      "ボーク": "3",
      "自責点": "394",
      "被打率": "0.240",
      "K/BB": "2.93",
      "WHIP": "1.23",
      "アウト": "3005.0",
      "故意四球": "7",
      "打者": "4174",
      "被打数": "3841",
      "打席": "4279",
      "打数": "3705",
      "安打": "914",
      "二塁打": "150",
      "三塁打": "22",
      "塁打": "1375",
      "打点": "417",
      "三振": "771",
      "四球": "421",
      "死球": "55",
      "犠打": "77",
      "犠飛": "21",
      "盗塁死": "31",
      "併殺打": "77",
      "出塁率": "0.331",
      "長打率": "0.371",
      "OPS": "0.702",
      "失策": "48"
    },
    {
      "チーム": "ソフトバンク",
      "League": "Pacific",
      "試合": "114",
      "勝利": "46",
      "敗戦": "49",
      "引分": "19",
      "勝率": ".484",
      "勝差": "3",
      "残試合": "29",
      "得点": "450",
      "失点": "391",
      "本塁打": "99",
      "盗塁": "68",
      "打率": ".248",
      "防御率": "3.25",
      "登板": "472",
      "先発": "106",
      "完投": "1",
      "完封": "0",
      "QS": "54",
      "ホールド": "76",
      "HP": "88",
      "セーブ": "21",
      "投球回": "946.1",
      "被安打": "782",
      "被本塁打": "92",
      "奪三振": "923",
      "奪三振率": "8.78",
      "与四球": "367",
      "与死球": "47",
      "暴投": "23",
      "ボーク": "0",
      "自責点": "348",
      "被打率": "0.221",
      "K/BB": "2.51",
      "WHIP": "1.21",
      "アウト": "2853.0",
      "故意四球": "8",
      "打者": "3945",
      "被打数": "3531",
      "打席": "4109",
      "打数": "3627",
      "安打": "902",
      "二塁打": "155",
      "三塁打": "20",
      "塁打": "1388",
      "打点": "421",
      "三振": "823",
      "四球": "356",
      "死球": "21",
      "犠打": "75",
      "犠飛": "30",
      "盗塁死": "26",
      "併殺打": "63",
      "出塁率": "0.317",
      "長打率": "0.383",
      "OPS": "0.700",
      "失策": "35"
    },
    {
      "チーム": "西武",
      "League": "Pacific",
      "試合": "114",
      "勝利": "43",
      "敗戦": "53",
      "引分": "18",
      "勝率": ".448",
      "勝差": "3.5",
      "残試合": "29",
      "得点": "434",
      "失点": "483",
      "本塁打": "90",
      "盗塁": "73",
      "打率": ".246",
      "防御率": "4.04",
      "登板": "501",
      "先発": "108",
      "完投": "2",
      "完封": "1",
      "QS": "43",
      "ホールド": "82",
      "HP": "90",
      "セーブ": "25",
      "投球回": "966.9",
      "被安打": "930",
      "被本塁打": "90",
      "奪三振": "749",
      "奪三振率": "6.96",
      "与四球": "461",
      "与死球": "52",
      "暴投": "55",
      "ボーク": "3",
      "自責点": "433",
      "被打率": "0.251",
      "K/BB": "1.62",
      "WHIP": "1.44",
      "アウト": "2921.0",
      "故意四球": "7",
      "打者": "4212",
      "被打数": "3699",
      "打席": "4168",
      "打数": "3680",
      "安打": "911",
      "二塁打": "164",
      "三塁打": "20",
      "塁打": "1382",
      "打点": "411",
      "三振": "804",
      "四球": "342",
      "死球": "47",
      "犠打": "65",
      "犠飛": "34",
      "盗塁死": "36",
      "併殺打": "74",
      "出塁率": "0.317",
      "長打率": "0.376",
      "OPS": "0.692",
      "失策": "52"
    },
    {
      "チーム": "日本ハム",
      "League": "Pacific",
      "試合": "109",
      "勝利": "40",
      "敗戦": "52",
      "引分": "17",
      "勝率": ".435",
      "勝差": "1",
      "残試合": "34",
      "得点": "353",
      "失点": "414",
      "本塁打": "59",
      "盗塁": "59",
      "打率": ".232",
      "防御率": "3.47",
      "登板": "452",
      "先発": "109",
      "完投": "2",
      "完封": "1",
      "QS": "50",
      "ホールド": "90",
      "HP": "99",
      "セーブ": "23",
      "投球回": "940.7",
      "被安打": "868",
      "被本塁打": "73",
      "奪三振": "795",
      "奪三振率": "7.59",
      "与四球": "342",
      "与死球": "49",
      "暴投": "31",
      "ボーク": "3",
      "自責点": "365",
      "被打率": "0.254",
      "K/BB": "2.32",
      "WHIP": "1.28",
      "アウト": "2841.0",
      "故意四球": "17",
      "打者": "3807",
      "被打数": "3416",
      "打席": "3782",
      "打数": "3309",
      "安打": "775",
      "二塁打": "145",
      "三塁打": "17",
      "塁打": "1119",
      "打点": "325",
      "三振": "873",
      "四球": "348",
      "死球": "32",
      "犠打": "68",
      "犠飛": "25",
      "盗塁死": "26",
      "併殺打": "69",
      "出塁率": "0.311",
      "長打率": "0.338",
      "OPS": "0.649",
      "失策": "52"
    }
  ]
}