{
  "Team": [
    {
      "チーム": "阪神",
      "League": "Central",
      "試合": "13",
      "勝利": "9",
      "敗戦": "4",
      "引分": "0",
      "勝率": ".692",
      "勝差": "0",
      "残試合": "130",
      "得点": "58",
      "失点": "33",
      "本塁打": "11",
      "盗塁": "7",
      "打率": ".253",
      "防御率": "2.63",
      "登板": "46",
      "先発": "13",
      "完投": "1",
      "完封": "0",
      "QS": "10",
      "ホールド": "8",
      "HP": "10",
      "セーブ": "2",
      "投球回": "111.6",
      "被安打": "94",
      "被本塁打": "9",
      "奪三振": "87",
      "奪三振率": "6.93",
      "与四球": "34",
      "与死球": "4",
      "暴投": "5",
      "ボーク": "1",
      "自責点": "33",
      "被打率": "0.240",
      "K/BB": "2.56",
      "WHIP": "1.13",
      "アウト": "339.0",
      "故意四球": "3",
      "打者": "429",
      "被打数": "391",
      "打席": "448",
      "打数": "397",
      "安打": "105",
      "二塁打": "21",
      "三塁打": "1",
      "塁打": "161",
      "打点": "57",
      "三振": "90",
      "四球": "35",
      "死球": "3",
      "犠打": "4",
      "犠飛": "9",
      "盗塁死": "0",
      "併殺打": "6",
      "出塁率": "0.322",
      "長打率": "0.406",
      "OPS": "0.728",
      "失策": "10"
    },
    {
      "チーム": "広島",
      "League": "Central",
      "試合": "13",
      "勝利": "7",
      "敗戦": "5",
      "引分": "1",
      "勝率": ".583",
      "勝差": "1.5",
      "残試合": "130",
      "得点": "43",
      "失点": "36",
      "本塁打": "15",
      "盗塁": "3",
      "打率": ".254",
      "防御率": "2.45",
      "登板": "49",
      "先発": "13",
      "完投": "1",
      "完封": "1",
      "QS": "9",
      "ホールド": "12",
      "HP": "12",
      "セーブ": "4",
      "投球回": "111.9",
      "被安打": "96",
      "被本塁打": "6",
      "奪三振": "86",
      "奪三振率": "6.79",
      "与四球": "34",
      "与死球": "1",
      "暴投": "5",
      "ボーク": "0",
      "自責点": "31",
      "被打率": "0.246",
      "K/BB": "2.53",
      "WHIP": "1.14",
      "アウト": "342.0",
      "故意四球": "1",
      "打者": "426",
      "被打数": "391",
      "打席": "443",
      "打数": "393",
      "安打": "105",
      "二塁打": "14",
      "三塁打": "0",
      "塁打": "164",
      "打点": "42",
      "三振": "71",
      "四球": "42",
      "死球": "3",
      "犠打": "5",
      "犠飛": "0",
      "盗塁死": "4",
      "併殺打": "10",
      "出塁率": "0.342",
      "長打率": "0.417",
      "OPS": "0.760",
      "失策": "6"
    },
    {
      "チーム": "巨人",
      "League": "Central",
      "試合": "13",
      "勝利": "5",
      "敗戦": "5",
      "引分": "3",
      "勝率": ".500",
      "勝差": "1",
      "残試合": "130",
      "得点": "38",
      "失点": "42",
      "本塁打": "8",
      "盗塁": "10",
      "打率": ".219",
      "防御率": "2.97",
      "登板": "49",
      "先発": "13",
      "完投": "0",
      "完封": "0",
      "QS": "10",
      "ホールド": "6",
      "HP": "7",
      "セーブ": "3",
      "投球回": "109.9",
      "被安打": "100",
      "被本塁打": "6",
      "奪三振": "97",
      "奪三振率": "7.79",
      "与四球": "30",
      "与死球": "5",
      "暴投": "6",
      "ボーク": "0",
      "自責点": "37",
      "被打率": "0.249",
      "K/BB": "3.23",
      "WHIP": "1.16",
      "アウト": "336.0",
      "故意四球": "0",
      "打者": "437",
      "被打数": "402",
      "打席": "432",
      "打数": "384",
      "安打": "89",
      "二塁打": "21",
      "三塁打": "2",
      "塁打": "138",
      "打点": "34",
      "三振": "86",
      "四球": "43",
      "死球": "2",
      "犠打": "2",
      "犠飛": "1",
      "盗塁死": "4",
      "併殺打": "9",
      "出塁率": "0.312",
      "長打率": "0.359",
      "OPS": "0.671",
      "失策": "8"
    },
    {
      "チーム": "ヤクルト",
      "League": "Central",
      "試合": "12",
      "勝利": "5",
      "敗戦": "5",
      "引分": "2",
      "勝率": ".500",
      "勝差": "0",
      "残試合": "131",
      "得点": "50",
      "失点": "54",
      "本塁打": "9",
      "盗塁": "9",
      "打率": ".251",
      "防御率": "4.29",
      "登板": "58",
      "先発": "12",
      "完投": "0",
      "完封": "0",
      "QS": "3",
      "ホールド": "10",
      "HP": "12",
      "セーブ": "4",
      "投球回": "104.2",
      "被安打": "106",
      "被本塁打": "12",
      "奪三振": "88",
      "奪三振率": "7.57",
      "与四球": "36",
      "与死球": "2",
      "暴投": "4",
      "ボーク": "0",
      "自責点": "51",
      "被打率": "0.271",
      "K/BB": "2.44",
      "WHIP": "1.36",
      "アウト": "321.0",
      "故意四球": "0",
      "打者": "429",
      "被打数": "391",
      "打席": "435",
      "打数": "383",
      "安打": "99",
      "二塁打": "17",
      "三塁打": "1",
      "塁打": "145",
      "打点": "48",
      "三振": "79",
      "四球": "35",
      "死球": "5",
      "犠打": "8",
      "犠飛": "4",
      "盗塁死": "2",
      "併殺打": "8",
      "出塁率": "0.326",
      "長打率": "0.379",
      "OPS": "0.704",
      "失策": "4"
    },
    {
      "チーム": "中日",
      "League": "Central",
      "試合": "12",
      "勝利": "4",
      "敗戦": "6",
      "引分": "2",
      "勝率": ".400",
      "勝差": "1",
      "残試合": "131",
      "得点": "32",
      "失点": "39",
      "本塁打": "1",
      "盗塁": "7",
      "打率": ".216",
      "防御率": "2.56",
      "登板": "57",
      "先発": "12",
      "完投": "0",
      "完封": "0",
      "QS": "4",
      "ホールド": "14",
      "HP": "17",
      "セーブ": "4",
      "投球回": "102.4",
      "被安打": "97",
      "被本塁打": "8",
      "奪三振": "86",
      "奪三振率": "7.49",
      "与四球": "32",
      "与死球": "2",
      "暴投": "0",
      "ボーク": "0",
      "自責点": "30",
      "被打率": "0.237",
      "K/BB": "2.69",
      "WHIP": "1.25",
      "アウト": "317.0",
      "故意四球": "2",
      "打者": "444",
      "被打数": "410",
      "打席": "410",
      "打数": "376",
      "安打": "83",
      "二塁打": "20",
      "三塁打": "3",
      "塁打": "112",
      "打点": "26",
      "三振": "67",
      "四球": "27",
      "死球": "3",
      "犠打": "4",
      "犠飛": "0",
      "盗塁死": "1",
      "併殺打": "6",
      "出塁率": "0.278",
      "長打率": "0.298",
      "OPS": "0.576",
      "失策": "10"
    },
    {
      "チーム": "ＤｅＮＡ",
      "League": "Central",
      "試合": "13",
      "勝利": "3",
      "敗戦": "8",
      "引分": "2",
      "勝率": ".273",
      "勝差": "1.5",
      "残試合": "130",
      "得点": "52",
      "失点": "69",
      "本塁打": "8",
      "盗塁": "3",
      "打率": ".264",
      "防御率": "5.05",
      "登板": "64",
      "先発": "13",
      "完投": "0",
      "完封": "0",
      "QS": "2",
      "ホールド": "11",
      "HP": "12",
      "セーブ": "2",
      "投球回": "110.9",
      "被安打": "109",
      "被本塁打": "10",
      "奪三振": "98",
      "奪三振率": "7.81",
      "与四球": "52",
      "与死球": "2",
      "暴投": "5",
      "ボーク": "1",
      "自責点": "58",
      "被打率": "0.282",
      "K/BB": "1.88",
      "WHIP": "1.42",
      "アウト": "339.0",
      "故意四球": "2",
      "打者": "441",
      "被打数": "387",
      "打席": "478",
      "打数": "433",
      "安打": "118",
      "二塁打": "22",
      "三塁打": "1",
      "塁打": "166",
      "打点": "49",
      "三振": "86",
      "四球": "31",
      "死球": "1",
      "犠打": "10",
      "犠飛": "3",
      "盗塁死": "2",
      "併殺打": "7",
      "出塁率": "0.321",
      "長打率": "0.383",
      "OPS": "0.704",
      "失策": "6"
    },
    {
      "チーム": "楽天",
      "League": "Pacific",
      "試合": "13",
      "勝利": "9",
      "敗戦": "3",
      "引分": "1",
      "勝率": ".750",
      "勝差": "0",
      "残試合": "130",
      "得点": "60",
      "失点": "42",
      "本塁打": "14",
      "盗塁": "3",
      "打率": ".241",
      "防御率": "3.10",
      "登板": "50",
      "先発": "13",
      "完投": "1",
      "完封": "1",
      "QS": "9",
      "ホールド": "6",
      "HP": "7",
      "セーブ": "3",
      "投球回": "113.2",
      "被安打": "94",
      "被本塁打": "5",
      "奪三振": "83",
      "奪三振率": "6.57",
      "与四球": "42",
      "与死球": "6",
      "暴投": "2",
      "ボーク": "0",
      "自責点": "40",
      "被打率": "0.239",
      "K/BB": "1.98",
      "WHIP": "1.20",
      "アウト": "348.0",
      "故意四球": "0",
      "打者": "442",
      "被打数": "394",
      "打席": "502",
      "打数": "420",
      "安打": "101",
      "二塁打": "15",
      "三塁打": "2",
      "塁打": "162",
      "打点": "58",
      "三振": "85",
      "四球": "72",
      "死球": "6",
      "犠打": "4",
      "犠飛": "0",
      "盗塁死": "7",
      "併殺打": "9",
      "出塁率": "0.359",
      "長打率": "0.386",
      "OPS": "0.745",
      "失策": "9"
    },
    {
      "チーム": "西武",
      "League": "Pacific",
      "試合": "12",
      "勝利": "7",
      "敗戦": "4",
      "引分": "1",
      "勝率": ".636",
      "勝差": "1.5",
      "残試合": "131",
      "得点": "52",
      "失点": "47",
      "本塁打": "12",
      "盗塁": "15",
      "打率": ".234",
      "防御率": "3.92",
      "登板": "55",
      "先発": "12",
      "完投": "0",
      "完封": "0",
      "QS": "3",
      "ホールド": "8",
      "HP": "9",
      "セーブ": "4",
      "投球回": "104.5",
      "被安打": "96",
      "被本塁打": "13",
      "奪三振": "93",
      "奪三振率": "7.92",
      "与四球": "59",
      "与死球": "7",
      "暴投": "10",
      "ボーク": "0",
      "自責点": "47",
      "被打率": "0.258",
      "K/BB": "1.58",
      "WHIP": "1.47",
      "アウト": "324.0",
      "故意四球": "1",
      "打者": "438",
      "被打数": "372",
      "打席": "442",
      "打数": "385",
      "安打": "90",
      "二塁打": "12",
      "三塁打": "2",
      "塁打": "142",
      "打点": "50",
      "三振": "89",
      "四球": "34",
      "死球": "9",
      "犠打": "8",
      "犠飛": "6",
      "盗塁死": "7",
      "併殺打": "5",
      "出塁率": "0.306",
      "長打率": "0.369",
      "OPS": "0.675",
      "失策": "4"
    },
    {
      "チーム": "ソフトバンク",
      "League": "Pacific",
      "試合": "13",
      "勝利": "7",
      "敗戦": "5",
      "引分": "1",
      "勝率": ".583",
      "勝差": "0.5",
      "残試合": "130",
      "得点": "48",
      "失点": "41",
      "本塁打": "13",
      "盗塁": "2",
      "打率": ".234",
      "防御率": "3.13",
      "登板": "60",
      "先発": "13",
      "完投": "0",
      "完封": "0",
      "QS": "6",
      "ホールド": "8",
      "HP": "12",
      "セーブ": "2",
      "投球回": "112.2",
      "被安打": "86",
      "被本塁打": "9",
      "奪三振": "109",
      "奪三振率": "8.71",
      "与四球": "67",
      "与死球": "6",
      "暴投": "2",
      "ボーク": "0",
      "自責点": "40",
      "被打率": "0.224",
      "K/BB": "1.63",
      "WHIP": "1.36",
      "アウト": "345.0",
      "故意四球": "1",
      "打者": "457",
      "被打数": "384",
      "打席": "478",
      "打数": "422",
      "安打": "98",
      "二塁打": "24",
      "三塁打": "0",
      "塁打": "158",
      "打点": "44",
      "三振": "108",
      "四球": "45",
      "死球": "0",
      "犠打": "7",
      "犠飛": "4",
      "盗塁死": "2",
      "併殺打": "8",
      "出塁率": "0.304",
      "長打率": "0.374",
      "OPS": "0.678",
      "失策": "3"
    },
    {
      "チーム": "オリックス",
      "League": "Pacific",
      "試合": "13",
      "勝利": "5",
      "敗戦": "7",
      "引分": "1",
      "勝率": ".417",
      "勝差": "2",
      "残試合": "130",
      "得点": "36",
      "失点": "38",
      "本塁打": "8",
      "盗塁": "3",
      "打率": ".211",
      "防御率": "2.49",
      "登板": "43",
      "先発": "13",
      "完投": "1",
      "完封": "1",
      "QS": "8",
      "ホールド": "3",
      "HP": "3",
      "セーブ": "2",
      "投球回": "109.9",
      "被安打": "78",
      "被本塁打": "8",
      "奪三振": "100",
      "奪三振率": "8.04",
      "与四球": "42",
      "与死球": "7",
      "暴投": "3",
      "ボーク": "0",
      "自責点": "31",
      "被打率": "0.209",
      "K/BB": "2.38",
      "WHIP": "1.07",
      "アウト": "336.0",
      "故意四球": "2",
      "打者": "423",
      "被打数": "374",
      "打席": "443",
      "打数": "390",
      "安打": "84",
      "二塁打": "16",
      "三塁打": "1",
      "塁打": "123",
      "打点": "32",
      "三振": "87",
      "四球": "37",
      "死球": "5",
      "犠打": "8",
      "犠飛": "3",
      "盗塁死": "2",
      "併殺打": "6",
      "出塁率": "0.290",
      "長打率": "0.315",
      "OPS": "0.605",
      "失策": "11"
    },
    {
      "チーム": "ロッテ",
      "League": "Pacific",
      "試合": "13",
      "勝利": "4",
      "敗戦": "7",
      "引分": "2",
      "勝率": ".364",
      "勝差": "0.5",
      "残試合": "130",
      "得点": "66",
      "失点": "56",
      "本塁打": "14",
      "盗塁": "7",
      "打率": ".228",
      "防御率": "4.23",
      "登板": "50",
      "先発": "13",
      "完投": "0",
      "完封": "0",
      "QS": "6",
      "ホールド": "7",
      "HP": "8",
      "セーブ": "1",
      "投球回": "113.6",
      "被安打": "95",
      "被本塁打": "16",
      "奪三振": "94",
      "奪三振率": "7.36",
      "与四球": "52",
      "与死球": "1",
      "暴投": "1",
      "ボーク": "0",
      "自責点": "54",
      "被打率": "0.245",
      "K/BB": "1.81",
      "WHIP": "1.28",
      "アウト": "345.0",
      "故意四球": "1",
      "打者": "441",
      "被打数": "388",
      "打席": "490",
      "打数": "411",
      "安打": "95",
      "二塁打": "27",
      "三塁打": "1",
      "塁打": "166",
      "打点": "62",
      "三振": "80",
      "四球": "60",
      "死球": "7",
      "犠打": "8",
      "犠飛": "4",
      "盗塁死": "2",
      "併殺打": "9",
      "出塁率": "0.336",
      "長打率": "0.404",
      "OPS": "0.740",
      "失策": "1"
    },
    {
      "チーム": "日本ハム",
      "League": "Pacific",
      "試合": "12",
      "勝利": "2",
      "敗戦": "8",
      "引分": "2",
      "勝率": ".200",
      "勝差": "1.5",
      "残試合": "131",
      "得点": "32",
      "失点": "70",
      "本塁打": "1",
      "盗塁": "8",
      "打率": ".214",
      "防御率": "5.09",
      "登板": "53",
      "先発": "12",
      "完投": "0",
      "完封": "0",
      "QS": "4",
      "ホールド": "8",
      "HP": "9",
      "セーブ": "1",
      "投球回": "97.4",
      "被安打": "103",
      "被本塁打": "10",
      "奪三振": "85",
      "奪三振率": "7.78",
      "与四球": "46",
      "与死球": "3",
      "暴投": "3",
      "ボーク": "0",
      "自責点": "58",
      "被打率": "0.285",
      "K/BB": "1.85",
      "WHIP": "1.52",
      "アウト": "302.0",
      "故意四球": "1",
      "打者": "411",
      "被打数": "362",
      "打席": "448",
      "打数": "380",
      "安打": "81",
      "二塁打": "12",
      "三塁打": "3",
      "塁打": "102",
      "打点": "28",
      "三振": "106",
      "四球": "59",
      "死球": "2",
      "犠打": "7",
      "犠飛": "0",
      "盗塁死": "2",
      "併殺打": "6",
      "出塁率": "0.322",
      "長打率": "0.268",
      "OPS": "0.590",
      "失策": "7"
    }
  ]
}